{
"meta":{"test_sets":[],"test_metrics":[],"learn_metrics":[{"best_value":"Min","name":"RMSE"}],"launch_mode":"Train","parameters":"","iteration_count":1000,"learn_sets":["learn"],"name":"experiment"},
"iterations":[
{"learn":[14.61268541],"iteration":0,"passed_time":0.05821473304,"remaining_time":58.15651831},
{"learn":[14.23196558],"iteration":1,"passed_time":0.05842636086,"remaining_time":29.15475407},
{"learn":[13.86674177],"iteration":2,"passed_time":0.05866848908,"remaining_time":19.49749454},
{"learn":[13.49946468],"iteration":3,"passed_time":0.05888661698,"remaining_time":14.66276763},
{"learn":[13.16661202],"iteration":4,"passed_time":0.05909678645,"remaining_time":11.7602605},
{"learn":[12.85632158],"iteration":5,"passed_time":0.05939295706,"remaining_time":9.839433219},
{"learn":[12.56784336],"iteration":6,"passed_time":0.05961266831,"remaining_time":8.456482805},
{"learn":[12.31617801],"iteration":7,"passed_time":0.05982625449,"remaining_time":7.418455557},
{"learn":[12.01509946],"iteration":8,"passed_time":0.06005092414,"remaining_time":6.612273981},
{"learn":[11.71512571],"iteration":9,"passed_time":0.06027213542,"remaining_time":5.966941407},
{"learn":[11.43264457],"iteration":10,"passed_time":0.06047259642,"remaining_time":5.437036169},
{"learn":[11.17973129],"iteration":11,"passed_time":0.06069297436,"remaining_time":4.997054889},
{"learn":[10.93746433],"iteration":12,"passed_time":0.0609041855,"remaining_time":4.624033161},
{"learn":[10.69387075],"iteration":13,"passed_time":0.06110752154,"remaining_time":4.303715446},
{"learn":[10.4615922],"iteration":14,"passed_time":0.06131331594,"remaining_time":4.02624108},
{"learn":[10.2299235],"iteration":15,"passed_time":0.0615081102,"remaining_time":3.782748777},
{"learn":[10.01419731],"iteration":16,"passed_time":0.06172652978,"remaining_time":3.56924581},
{"learn":[9.795856918],"iteration":17,"passed_time":0.06192819913,"remaining_time":3.378527308},
{"learn":[9.60040151],"iteration":18,"passed_time":0.06213224351,"remaining_time":3.207985836},
{"learn":[9.418664989],"iteration":19,"passed_time":0.06236287158,"remaining_time":3.055780707},
{"learn":[9.249278645],"iteration":20,"passed_time":0.06255891585,"remaining_time":2.916437077},
{"learn":[9.090113396],"iteration":21,"passed_time":0.06275979353,"remaining_time":2.789958094},
{"learn":[8.909548708],"iteration":22,"passed_time":0.06295637948,"remaining_time":2.674277511},
{"learn":[8.740140208],"iteration":23,"passed_time":0.06315575713,"remaining_time":2.568334123},
{"learn":[8.59377682],"iteration":24,"passed_time":0.06336913497,"remaining_time":2.471396264},
{"learn":[8.453885414],"iteration":25,"passed_time":0.06356951264,"remaining_time":2.381411743},
{"learn":[8.317732234],"iteration":26,"passed_time":0.06377505704,"remaining_time":2.298264093},
{"learn":[8.180896085],"iteration":27,"passed_time":0.06397093464,"remaining_time":2.220705303},
{"learn":[8.053220863],"iteration":28,"passed_time":0.06417131231,"remaining_time":2.14863256},
{"learn":[7.924234474],"iteration":29,"passed_time":0.06437848173,"remaining_time":2.081570909},
{"learn":[7.818879511],"iteration":30,"passed_time":0.06456585923,"remaining_time":2.018203793},
{"learn":[7.719346395],"iteration":31,"passed_time":0.06475019501,"remaining_time":1.958693399},
{"learn":[7.624163594],"iteration":32,"passed_time":0.06492869739,"remaining_time":1.902607587},
{"learn":[7.524952543],"iteration":33,"passed_time":0.06513328345,"remaining_time":1.850551524},
{"learn":[7.424464745],"iteration":34,"passed_time":0.06534686962,"remaining_time":1.801706548},
{"learn":[7.327482321],"iteration":35,"passed_time":0.06553799717,"remaining_time":1.754961924},
{"learn":[7.238666841],"iteration":36,"passed_time":0.06573637481,"remaining_time":1.710922404},
{"learn":[7.158842395],"iteration":37,"passed_time":0.06593304409,"remaining_time":1.669147064},
{"learn":[7.074348246],"iteration":38,"passed_time":0.06612229661,"remaining_time":1.629321206},
{"learn":[6.992269093],"iteration":39,"passed_time":0.06643121739,"remaining_time":1.594349217},
{"learn":[6.925219745],"iteration":40,"passed_time":0.06662455329,"remaining_time":1.558364551},
{"learn":[6.86013671],"iteration":41,"passed_time":0.06685038963,"remaining_time":1.524825554},
{"learn":[6.786739622],"iteration":42,"passed_time":0.067053809,"remaining_time":1.492337098},
{"learn":[6.73057926],"iteration":43,"passed_time":0.06725189497,"remaining_time":1.461200264},
{"learn":[6.666356486],"iteration":44,"passed_time":0.06743848079,"remaining_time":1.431194426},
{"learn":[6.606182832],"iteration":45,"passed_time":0.06761885819,"remaining_time":1.40235632},
{"learn":[6.547854615],"iteration":46,"passed_time":0.06781323578,"remaining_time":1.375021568},
{"learn":[6.49240675],"iteration":47,"passed_time":0.06800886338,"remaining_time":1.348842457},
{"learn":[6.431317261],"iteration":48,"passed_time":0.06821799116,"remaining_time":1.32398591},
{"learn":[6.377586395],"iteration":49,"passed_time":0.06843782742,"remaining_time":1.300318721},
{"learn":[6.327558015],"iteration":50,"passed_time":0.06863662173,"remaining_time":1.277179491},
{"learn":[6.282040317],"iteration":51,"passed_time":0.06883341602,"remaining_time":1.254886123},
{"learn":[6.237655841],"iteration":52,"passed_time":0.0690349187,"remaining_time":1.233510717},
{"learn":[6.192792003],"iteration":53,"passed_time":0.06925171325,"remaining_time":1.213187421},
{"learn":[6.150579347],"iteration":54,"passed_time":0.06945817433,"remaining_time":1.193417723},
{"learn":[6.115693845],"iteration":55,"passed_time":0.06966284372,"remaining_time":1.174316509},
{"learn":[6.078780782],"iteration":56,"passed_time":0.06986784645,"remaining_time":1.155883846},
{"learn":[6.045146957],"iteration":57,"passed_time":0.0700668491,"remaining_time":1.137982273},
{"learn":[6.008080327],"iteration":58,"passed_time":0.07039414512,"remaining_time":1.122726959},
{"learn":[5.977575734],"iteration":59,"passed_time":0.07058706436,"remaining_time":1.105864008},
{"learn":[5.948036502],"iteration":60,"passed_time":0.07078402531,"remaining_time":1.089609832},
{"learn":[5.914888282],"iteration":61,"passed_time":0.0709960698,"remaining_time":1.07410183},
{"learn":[5.884957796],"iteration":62,"passed_time":0.07118486398,"remaining_time":1.058733612},
{"learn":[5.849539885],"iteration":63,"passed_time":0.07138269995,"remaining_time":1.043971987},
{"learn":[5.821387627],"iteration":64,"passed_time":0.07157474417,"remaining_time":1.029575166},
{"learn":[5.797012279],"iteration":65,"passed_time":0.07189420675,"remaining_time":1.017411956},
{"learn":[5.768685095],"iteration":66,"passed_time":0.07216116864,"remaining_time":1.004871199},
{"learn":[5.755484587],"iteration":67,"passed_time":0.07227029509,"remaining_time":0.9905281621},
{"learn":[5.731887055],"iteration":68,"passed_time":0.0724488808,"remaining_time":0.9775348989},
{"learn":[5.707148487],"iteration":69,"passed_time":0.07265484187,"remaining_time":0.9652714706},
{"learn":[5.685365039],"iteration":70,"passed_time":0.07284126102,"remaining_time":0.9530919928},
{"learn":[5.663541834],"iteration":71,"passed_time":0.07304497207,"remaining_time":0.9414685289},
{"learn":[5.638108797],"iteration":72,"passed_time":0.07322905785,"remaining_time":0.9299087209},
{"learn":[5.619204893],"iteration":73,"passed_time":0.07344310236,"remaining_time":0.9190312539},
{"learn":[5.598472793],"iteration":74,"passed_time":0.07363443824,"remaining_time":0.9081580717},
{"learn":[5.577007075],"iteration":75,"passed_time":0.07385660787,"remaining_time":0.8979408641},
{"learn":[5.562637084],"iteration":76,"passed_time":0.07406648566,"remaining_time":0.8878359255},
{"learn":[5.54729991],"iteration":77,"passed_time":0.07431257227,"remaining_time":0.8784127132},
{"learn":[5.530737623],"iteration":78,"passed_time":0.07450807487,"remaining_time":0.8686321134},
{"learn":[5.513704873],"iteration":79,"passed_time":0.07473945295,"remaining_time":0.8595037089},
{"learn":[5.501575529],"iteration":80,"passed_time":0.07492283039,"remaining_time":0.8500503843},
{"learn":[5.484080734],"iteration":81,"passed_time":0.07515375013,"remaining_time":0.8413553978},
{"learn":[5.472178894],"iteration":82,"passed_time":0.07537637809,"remaining_time":0.8327727556},
{"learn":[5.458923342],"iteration":83,"passed_time":0.07558225583,"remaining_time":0.8242065041},
{"learn":[5.451382371],"iteration":84,"passed_time":0.07567746543,"remaining_time":0.8146456573},
{"learn":[5.441410748],"iteration":85,"passed_time":0.07588709322,"remaining_time":0.8065209675},
{"learn":[5.434047468],"iteration":86,"passed_time":0.07597371938,"remaining_time":0.7972874229},
{"learn":[5.422107497],"iteration":87,"passed_time":0.07617384704,"remaining_time":0.7894380511},
{"learn":[5.40731265],"iteration":88,"passed_time":0.07635622447,"remaining_time":0.7815788819},
{"learn":[5.396360181],"iteration":89,"passed_time":0.07656251888,"remaining_time":0.7741321353},
{"learn":[5.383793239],"iteration":90,"passed_time":0.07675922983,"remaining_time":0.7667487903},
{"learn":[5.369605034],"iteration":91,"passed_time":0.07695335741,"remaining_time":0.7594961797},
{"learn":[5.357467333],"iteration":92,"passed_time":0.07719627731,"remaining_time":0.7528712207},
{"learn":[5.341109968],"iteration":93,"passed_time":0.07747540603,"remaining_time":0.7467310411},
{"learn":[5.330529276],"iteration":94,"passed_time":0.07767470034,"remaining_time":0.7399537243},
{"learn":[5.319862075],"iteration":95,"passed_time":0.07785470274,"remaining_time":0.7331317841},
{"learn":[5.313052243],"iteration":96,"passed_time":0.0780847058,"remaining_time":0.7269122612},
{"learn":[5.299677207],"iteration":97,"passed_time":0.07827445833,"remaining_time":0.7204445042},
{"learn":[5.287546698],"iteration":98,"passed_time":0.07845950246,"remaining_time":0.7140607244},
{"learn":[5.279803754],"iteration":99,"passed_time":0.07865592174,"remaining_time":0.7079032956},
{"learn":[5.272254612],"iteration":100,"passed_time":0.07889029985,"remaining_time":0.7022017779},
{"learn":[5.268813888],"iteration":101,"passed_time":0.0790087181,"remaining_time":0.6955865574},
{"learn":[5.258113767],"iteration":102,"passed_time":0.07927809668,"remaining_time":0.6904121624},
{"learn":[5.251018576],"iteration":103,"passed_time":0.07947984937,"remaining_time":0.6847494715},
{"learn":[5.24171237],"iteration":104,"passed_time":0.07966168512,"remaining_time":0.6790210303},
{"learn":[5.233984943],"iteration":105,"passed_time":0.07984360421,"remaining_time":0.6733979449},
{"learn":[5.226240449],"iteration":106,"passed_time":0.08003377341,"remaining_time":0.6679454173},
{"learn":[5.220541644],"iteration":107,"passed_time":0.08021635917,"remaining_time":0.6625277072},
{"learn":[5.211712096],"iteration":108,"passed_time":0.08041219511,"remaining_time":0.6573143655},
{"learn":[5.203388597],"iteration":109,"passed_time":0.08062119789,"remaining_time":0.6522987829},
{"learn":[5.196026544],"iteration":110,"passed_time":0.08085036761,"remaining_time":0.6475313225},
{"learn":[5.188716772],"iteration":111,"passed_time":0.08103887011,"remaining_time":0.6425224702},
{"learn":[5.182163132],"iteration":112,"passed_time":0.08121120574,"remaining_time":0.6374720309},
{"learn":[5.17764747],"iteration":113,"passed_time":0.08142091687,"remaining_time":0.6327976521},
{"learn":[5.170548056],"iteration":114,"passed_time":0.0816340447,"remaining_time":0.6282272136},
{"learn":[5.165901827],"iteration":115,"passed_time":0.08177162987,"remaining_time":0.6231562138},
{"learn":[5.160333668],"iteration":116,"passed_time":0.08198325768,"remaining_time":0.6187283464},
{"learn":[5.148953243],"iteration":117,"passed_time":0.0821923438,"remaining_time":0.6143529426},
{"learn":[5.144729126],"iteration":118,"passed_time":0.08232980396,"remaining_time":0.6095172881},
{"learn":[5.139939946],"iteration":119,"passed_time":0.08253634838,"remaining_time":0.6052665548},
{"learn":[5.132898872],"iteration":120,"passed_time":0.08274864287,"remaining_time":0.6011244387},
{"learn":[5.129073077],"iteration":121,"passed_time":0.08296077069,"remaining_time":0.5970455464},
{"learn":[5.127123916],"iteration":122,"passed_time":0.08302981328,"remaining_time":0.592009319},
{"learn":[5.121282057],"iteration":123,"passed_time":0.08322673256,"remaining_time":0.5879565946},
{"learn":[5.114489821],"iteration":124,"passed_time":0.08341948513,"remaining_time":0.5839363959},
{"learn":[5.107777291],"iteration":125,"passed_time":0.08361173769,"remaining_time":0.579973482},
{"learn":[5.103518754],"iteration":126,"passed_time":0.0838054486,"remaining_time":0.5760799734},
{"learn":[5.101133351],"iteration":127,"passed_time":0.08390119987,"remaining_time":0.5715769241},
{"learn":[5.096462705],"iteration":128,"passed_time":0.08409786916,"remaining_time":0.5678235972},
{"learn":[5.08562082],"iteration":129,"passed_time":0.08432087212,"remaining_time":0.5643012211},
{"learn":[5.080483682],"iteration":130,"passed_time":0.08451024964,"remaining_time":0.5606061599},
{"learn":[5.07437499],"iteration":131,"passed_time":0.08471437736,"remaining_time":0.5570612087},
{"learn":[5.070683732],"iteration":132,"passed_time":0.08489083804,"remaining_time":0.5533861397},
{"learn":[5.06432037],"iteration":133,"passed_time":0.08505971529,"remaining_time":0.5497142794},
{"learn":[5.057436484],"iteration":134,"passed_time":0.08526130131,"remaining_time":0.5463038936},
{"learn":[5.053254656],"iteration":135,"passed_time":0.08544376207,"remaining_time":0.5428191943},
{"learn":[5.04801663],"iteration":136,"passed_time":0.08568947367,"remaining_time":0.5397811371},
{"learn":[5.045680836],"iteration":137,"passed_time":0.08582801718,"remaining_time":0.5361141363},
{"learn":[5.041857933],"iteration":138,"passed_time":0.08601393632,"remaining_time":0.532791361},
{"learn":[5.035264888],"iteration":139,"passed_time":0.08620498053,"remaining_time":0.5295448804},
{"learn":[5.028771948],"iteration":140,"passed_time":0.08639935812,"remaining_time":0.526362047},
{"learn":[5.024912247],"iteration":141,"passed_time":0.08659669408,"remaining_time":0.5232391797},
{"learn":[5.02239068],"iteration":142,"passed_time":0.08678132153,"remaining_time":0.5200810668},
{"learn":[5.017110572],"iteration":143,"passed_time":0.08704094999,"remaining_time":0.5174100916},
{"learn":[5.010707886],"iteration":144,"passed_time":0.08723507757,"remaining_time":0.5143861471},
{"learn":[5.004389868],"iteration":145,"passed_time":0.08746253893,"remaining_time":0.5115959469},
{"learn":[4.997628683],"iteration":146,"passed_time":0.08765445815,"remaining_time":0.5086343728},
{"learn":[4.991497851],"iteration":147,"passed_time":0.08787687778,"remaining_time":0.5058858099},
{"learn":[4.988345253],"iteration":148,"passed_time":0.08816250658,"remaining_time":0.5035321685},
{"learn":[4.98460423],"iteration":149,"passed_time":0.08848213583,"remaining_time":0.5013987697},
{"learn":[4.982441783],"iteration":150,"passed_time":0.0886977637,"remaining_time":0.4987046449},
{"learn":[4.977461771],"iteration":151,"passed_time":0.08890943319,"remaining_time":0.4960210483},
{"learn":[4.973601586],"iteration":152,"passed_time":0.08913251949,"remaining_time":0.4934329674},
{"learn":[4.968328804],"iteration":153,"passed_time":0.08940339809,"remaining_time":0.491138148},
{"learn":[4.9640736],"iteration":154,"passed_time":0.08959681733,"remaining_time":0.4884471655},
{"learn":[4.960865882],"iteration":155,"passed_time":0.08987307101,"remaining_time":0.4862363585},
{"learn":[4.957014156],"iteration":156,"passed_time":0.09005603178,"remaining_time":0.4835492662},
{"learn":[4.952244852],"iteration":157,"passed_time":0.09024670098,"remaining_time":0.4809349508},
{"learn":[4.949695675],"iteration":158,"passed_time":0.09043416181,"remaining_time":0.4783341515},
{"learn":[4.946584698],"iteration":159,"passed_time":0.09062508102,"remaining_time":0.4757816753},
{"learn":[4.940192834],"iteration":160,"passed_time":0.09082008361,"remaining_time":0.4732798146},
{"learn":[4.936727994],"iteration":161,"passed_time":0.0910197946,"remaining_time":0.4708307894},
{"learn":[4.932342063],"iteration":162,"passed_time":0.09121050548,"remaining_time":0.4683631478},
{"learn":[4.925830838],"iteration":163,"passed_time":0.09141242483,"remaining_time":0.4659804095},
{"learn":[4.922571773],"iteration":164,"passed_time":0.09159676062,"remaining_time":0.4635351219},
{"learn":[4.918395814],"iteration":165,"passed_time":0.0917856798,"remaining_time":0.4611401021},
{"learn":[4.911142452],"iteration":166,"passed_time":0.09199339089,"remaining_time":0.4588652372},
{"learn":[4.908276131],"iteration":167,"passed_time":0.09218031005,"remaining_time":0.4565120117},
{"learn":[4.904584645],"iteration":168,"passed_time":0.09236835422,"remaining_time":0.4541899548},
{"learn":[4.89795517],"iteration":169,"passed_time":0.09255544004,"remaining_time":0.4518883249},
{"learn":[4.895556491],"iteration":170,"passed_time":0.09274477589,"remaining_time":0.4496223346},
{"learn":[4.890591233],"iteration":171,"passed_time":0.0929304867,"remaining_time":0.4473630406},
{"learn":[4.884629277],"iteration":172,"passed_time":0.09312444761,"remaining_time":0.4451671571},
{"learn":[4.880550786],"iteration":173,"passed_time":0.09332107523,"remaining_time":0.4430069433},
{"learn":[4.876384842],"iteration":174,"passed_time":0.09355407833,"remaining_time":0.441040655},
{"learn":[4.872638238],"iteration":175,"passed_time":0.09377533128,"remaining_time":0.439039051},
{"learn":[4.869137118],"iteration":176,"passed_time":0.09397370892,"remaining_time":0.4369512002},
{"learn":[4.863587157],"iteration":177,"passed_time":0.09418167002,"remaining_time":0.4349288357},
{"learn":[4.858028614],"iteration":178,"passed_time":0.09439504786,"remaining_time":0.4329515882},
{"learn":[4.853838176],"iteration":179,"passed_time":0.09460100893,"remaining_time":0.4309601518},
{"learn":[4.853462329],"iteration":180,"passed_time":0.09466546812,"remaining_time":0.4283481679},
{"learn":[4.851573196],"iteration":181,"passed_time":0.09484859556,"remaining_time":0.4262975339},
{"learn":[4.848442087],"iteration":182,"passed_time":0.09503709807,"remaining_time":0.4242913067},
{"learn":[4.845547104],"iteration":183,"passed_time":0.09521626712,"remaining_time":0.4222634455},
{"learn":[4.839868817],"iteration":184,"passed_time":0.09541647812,"remaining_time":0.4203482685},
{"learn":[4.836336958],"iteration":185,"passed_time":0.0956908151,"remaining_time":0.4187759327},
{"learn":[4.831124789],"iteration":186,"passed_time":0.0958785676,"remaining_time":0.4168410452},
{"learn":[4.827407333],"iteration":187,"passed_time":0.09608790372,"remaining_time":0.4150179671},
{"learn":[4.824088918],"iteration":188,"passed_time":0.09627686456,"remaining_time":0.4131245352},
{"learn":[4.820934539],"iteration":189,"passed_time":0.09650682596,"remaining_time":0.411423837},
{"learn":[4.816975227],"iteration":190,"passed_time":0.09671645375,"remaining_time":0.409652414},
{"learn":[4.812340486],"iteration":191,"passed_time":0.09691228969,"remaining_time":0.4078392191},
{"learn":[4.806402747],"iteration":192,"passed_time":0.09710975065,"remaining_time":0.4060495791},
{"learn":[4.801521788],"iteration":193,"passed_time":0.09730221154,"remaining_time":0.4042555799},
{"learn":[4.797601172],"iteration":194,"passed_time":0.09748092225,"remaining_time":0.4024212432},
{"learn":[4.792694629],"iteration":195,"passed_time":0.09768150826,"remaining_time":0.4006935339},
{"learn":[4.789794613],"iteration":196,"passed_time":0.09786542737,"remaining_time":0.3989133918},
{"learn":[4.785367055],"iteration":197,"passed_time":0.09807397181,"remaining_time":0.3972491182},
{"learn":[4.780376856],"iteration":198,"passed_time":0.09827647451,"remaining_time":0.3955751562},
{"learn":[4.776691261],"iteration":199,"passed_time":0.09847281045,"remaining_time":0.3938912418},
{"learn":[4.773470753],"iteration":200,"passed_time":0.09868589662,"remaining_time":0.3922887134},
{"learn":[4.77207327],"iteration":201,"passed_time":0.09888294091,"remaining_time":0.3906365686},
{"learn":[4.767347177],"iteration":202,"passed_time":0.09907681849,"remaining_time":0.3889863268},
{"learn":[4.763983068],"iteration":203,"passed_time":0.09926086261,"remaining_time":0.3873119933},
{"learn":[4.761588849],"iteration":204,"passed_time":0.09945878191,"remaining_time":0.3857060079},
{"learn":[4.758558086],"iteration":205,"passed_time":0.09966270129,"remaining_time":0.3841368195},
{"learn":[4.753678804],"iteration":206,"passed_time":0.09985595386,"remaining_time":0.3825399585},
{"learn":[4.746510889],"iteration":207,"passed_time":0.1000412897,"remaining_time":0.3809264491},
{"learn":[4.744840601],"iteration":208,"passed_time":0.1002526675,"remaining_time":0.3794251673},
{"learn":[4.741702222],"iteration":209,"passed_time":0.100464837,"remaining_time":0.3779391486},
{"learn":[4.739352853],"iteration":210,"passed_time":0.1006500061,"remaining_time":0.3763642408},
{"learn":[4.735539287],"iteration":211,"passed_time":0.100839717,"remaining_time":0.3748193253},
{"learn":[4.730726751],"iteration":212,"passed_time":0.1010320945,"remaining_time":0.3732969877},
{"learn":[4.726416092],"iteration":213,"passed_time":0.1012315555,"remaining_time":0.3718130964},
{"learn":[4.721293082],"iteration":214,"passed_time":0.101441225,"remaining_time":0.370378426},
{"learn":[4.718443695],"iteration":215,"passed_time":0.1016731864,"remaining_time":0.3690360098},
{"learn":[4.711627962],"iteration":216,"passed_time":0.1019418566,"remaining_time":0.3678362845},
{"learn":[4.709790764],"iteration":217,"passed_time":0.1021387342,"remaining_time":0.3663875696},
{"learn":[4.706913073],"iteration":218,"passed_time":0.1023447786,"remaining_time":0.3649829777},
{"learn":[4.703846389],"iteration":219,"passed_time":0.102543948,"remaining_time":0.3635649064},
{"learn":[4.701001135],"iteration":220,"passed_time":0.1027552424,"remaining_time":0.3622006057},
{"learn":[4.700380864],"iteration":221,"passed_time":0.1029286614,"remaining_time":0.3607139576},
{"learn":[4.695837486],"iteration":222,"passed_time":0.1031129139,"remaining_time":0.3592768344},
{"learn":[4.691242996],"iteration":223,"passed_time":0.1032941246,"remaining_time":0.3578403603},
{"learn":[4.690284609],"iteration":224,"passed_time":0.1034891689,"remaining_time":0.3564626928},
{"learn":[4.68827119],"iteration":225,"passed_time":0.1036978383,"remaining_time":0.3551421543},
{"learn":[4.686922425],"iteration":226,"passed_time":0.1038945493,"remaining_time":0.3537906898},
{"learn":[4.686085874],"iteration":227,"passed_time":0.1040918852,"remaining_time":0.352451471},
{"learn":[4.683230741],"iteration":228,"passed_time":0.1042747627,"remaining_time":0.3510735459},
{"learn":[4.6773487],"iteration":229,"passed_time":0.1044793071,"remaining_time":0.3497785497},
{"learn":[4.671462906],"iteration":230,"passed_time":0.1046618095,"remaining_time":0.3484196169},
{"learn":[4.664799601],"iteration":231,"passed_time":0.1048528954,"remaining_time":0.3470992398},
{"learn":[4.660979386],"iteration":232,"passed_time":0.1050428146,"remaining_time":0.3457847157},
{"learn":[4.656281279],"iteration":233,"passed_time":0.1052388172,"remaining_time":0.3444997177},
{"learn":[4.651997094],"iteration":234,"passed_time":0.1054231946,"remaining_time":0.3431861442},
{"learn":[4.650151977],"iteration":235,"passed_time":0.1056140722,"remaining_time":0.3419031827},
{"learn":[4.648478046],"iteration":236,"passed_time":0.1058103248,"remaining_time":0.3406467418},
{"learn":[4.646364602],"iteration":237,"passed_time":0.1060100358,"remaining_time":0.3394102826},
{"learn":[4.642635873],"iteration":238,"passed_time":0.1061969132,"remaining_time":0.3381416359},
{"learn":[4.640860821],"iteration":239,"passed_time":0.1064334581,"remaining_time":0.3370392839},
{"learn":[4.639446822],"iteration":240,"passed_time":0.1066195439,"remaining_time":0.3357852025},
{"learn":[4.637120072],"iteration":241,"passed_time":0.1068137965,"remaining_time":0.3345655277},
{"learn":[4.633769267],"iteration":242,"passed_time":0.1070038823,"remaining_time":0.3333413124},
{"learn":[4.630491517],"iteration":243,"passed_time":0.1072051767,"remaining_time":0.3321603015},
{"learn":[4.627813333],"iteration":244,"passed_time":0.1073971376,"remaining_time":0.3309585259},
{"learn":[4.622496304],"iteration":245,"passed_time":0.1075956819,"remaining_time":0.3297851387},
{"learn":[4.618979301],"iteration":246,"passed_time":0.1077972262,"remaining_time":0.3286287908},
{"learn":[4.616563458],"iteration":247,"passed_time":0.1079878537,"remaining_time":0.3274470404},
{"learn":[4.614759385],"iteration":248,"passed_time":0.1082140234,"remaining_time":0.3263804482},
{"learn":[4.61251363],"iteration":249,"passed_time":0.1084324847,"remaining_time":0.325297454},
{"learn":[4.608796693],"iteration":250,"passed_time":0.1086468625,"remaining_time":0.3242091634},
{"learn":[4.60847774],"iteration":251,"passed_time":0.1088586153,"remaining_time":0.3231200169},
{"learn":[4.605195659],"iteration":252,"passed_time":0.1090547013,"remaining_time":0.3219915488},
{"learn":[4.60103766],"iteration":253,"passed_time":0.1092271619,"remaining_time":0.3208010346},
{"learn":[4.599325598],"iteration":254,"passed_time":0.1094258312,"remaining_time":0.3196950755},
{"learn":[4.597012808],"iteration":255,"passed_time":0.1096139171,"remaining_time":0.3185654464},
{"learn":[4.594161533],"iteration":256,"passed_time":0.1098105447,"remaining_time":0.3174678393},
{"learn":[4.592197259],"iteration":257,"passed_time":0.1100184224,"remaining_time":0.3164095715},
{"learn":[4.58952828],"iteration":258,"passed_time":0.1102044249,"remaining_time":0.3152952852},
{"learn":[4.585816572],"iteration":259,"passed_time":0.1104515949,"remaining_time":0.3143622315},
{"learn":[4.582934052],"iteration":260,"passed_time":0.1106558476,"remaining_time":0.3133129171},
{"learn":[4.582234842],"iteration":261,"passed_time":0.1108387667,"remaining_time":0.3122099611},
{"learn":[4.57571562],"iteration":262,"passed_time":0.1110368943,"remaining_time":0.3111566202},
{"learn":[4.571197349],"iteration":263,"passed_time":0.1112173551,"remaining_time":0.310060505},
{"learn":[4.56723703],"iteration":264,"passed_time":0.111416191,"remaining_time":0.3090222657},
{"learn":[4.560335567],"iteration":265,"passed_time":0.1116259022,"remaining_time":0.3080203466},
{"learn":[4.554709345],"iteration":266,"passed_time":0.1118044879,"remaining_time":0.3069389124},
{"learn":[4.552806306],"iteration":267,"passed_time":0.1120066989,"remaining_time":0.3059287447},
{"learn":[4.550766241],"iteration":268,"passed_time":0.1121928264,"remaining_time":0.3048808776},
{"learn":[4.549216045],"iteration":269,"passed_time":0.1123737871,"remaining_time":0.3038254244},
{"learn":[4.547687452],"iteration":270,"passed_time":0.1125645397,"remaining_time":0.3028027653},
{"learn":[4.545642435],"iteration":271,"passed_time":0.1127482504,"remaining_time":0.3017673761},
{"learn":[4.543930359],"iteration":272,"passed_time":0.1129395446,"remaining_time":0.3007584211},
{"learn":[4.541029943],"iteration":273,"passed_time":0.1131332556,"remaining_time":0.2997618377},
{"learn":[4.537781449],"iteration":274,"passed_time":0.1133255081,"remaining_time":0.2987672487},
{"learn":[4.53066128],"iteration":275,"passed_time":0.1135267608,"remaining_time":0.2978020827},
{"learn":[4.526763956],"iteration":276,"passed_time":0.1137260968,"remaining_time":0.2968374295},
{"learn":[4.522036004],"iteration":277,"passed_time":0.1139105576,"remaining_time":0.2958396495},
{"learn":[4.515307629],"iteration":278,"passed_time":0.1141124769,"remaining_time":0.2948928167},
{"learn":[4.51109143],"iteration":279,"passed_time":0.1143121879,"remaining_time":0.2939456261},
{"learn":[4.508233494],"iteration":280,"passed_time":0.1145147739,"remaining_time":0.293011112},
{"learn":[4.502555629],"iteration":281,"passed_time":0.1147086099,"remaining_time":0.2920595102},
{"learn":[4.500081355],"iteration":282,"passed_time":0.1149021124,"remaining_time":0.2911124191},
{"learn":[4.495281743],"iteration":283,"passed_time":0.1150925733,"remaining_time":0.2901629665},
{"learn":[4.492138869],"iteration":284,"passed_time":0.1152854925,"remaining_time":0.2892250076},
{"learn":[4.491708261],"iteration":285,"passed_time":0.1154650366,"remaining_time":0.2882588676},
{"learn":[4.489398865],"iteration":286,"passed_time":0.1156443723,"remaining_time":0.2872976915},
{"learn":[4.485796373],"iteration":287,"passed_time":0.1158310831,"remaining_time":0.2863601777},
{"learn":[4.479542205],"iteration":288,"passed_time":0.1160386692,"remaining_time":0.2854792173},
{"learn":[4.475986993],"iteration":289,"passed_time":0.1162257967,"remaining_time":0.2845528126},
{"learn":[4.468661855],"iteration":290,"passed_time":0.1164395912,"remaining_time":0.2836964611},
{"learn":[4.463785664],"iteration":291,"passed_time":0.1166258437,"remaining_time":0.2827777306},
{"learn":[4.460445831],"iteration":292,"passed_time":0.1168334715,"remaining_time":0.2819155779},
{"learn":[4.45692492],"iteration":293,"passed_time":0.1170591828,"remaining_time":0.2811013029},
{"learn":[4.454031688],"iteration":294,"passed_time":0.1172991443,"remaining_time":0.2803250737},
{"learn":[4.451672391],"iteration":295,"passed_time":0.1175220223,"remaining_time":0.2795118368},
{"learn":[4.45031553],"iteration":296,"passed_time":0.1177170666,"remaining_time":0.2786366929},
{"learn":[4.446782666],"iteration":297,"passed_time":0.1179160692,"remaining_time":0.2777754382},
{"learn":[4.444369689],"iteration":298,"passed_time":0.1181169885,"remaining_time":0.2769231069},
{"learn":[4.44411683],"iteration":299,"passed_time":0.1183173245,"remaining_time":0.2760737573},
{"learn":[4.440876943],"iteration":300,"passed_time":0.1185121188,"remaining_time":0.2752158506},
{"learn":[4.439336453],"iteration":301,"passed_time":0.1186984546,"remaining_time":0.2743427858},
{"learn":[4.436666901],"iteration":302,"passed_time":0.1189337077,"remaining_time":0.2735867799},
{"learn":[4.433043336],"iteration":303,"passed_time":0.1191739609,"remaining_time":0.2728456474},
{"learn":[4.431419305],"iteration":304,"passed_time":0.1193698385,"remaining_time":0.2720066813},
{"learn":[4.428859646],"iteration":305,"passed_time":0.1195617994,"remaining_time":0.2711630353},
{"learn":[4.424552441],"iteration":306,"passed_time":0.1197652605,"remaining_time":0.2703495945},
{"learn":[4.422706391],"iteration":307,"passed_time":0.1199573047,"remaining_time":0.2695144638},
{"learn":[4.421427994],"iteration":308,"passed_time":0.120157724,"remaining_time":0.2687022243},
{"learn":[4.418733158],"iteration":309,"passed_time":0.1203381014,"remaining_time":0.2678493225},
{"learn":[4.415656941],"iteration":310,"passed_time":0.1205385208,"remaining_time":0.2670451473},
{"learn":[4.410747417],"iteration":311,"passed_time":0.1207474402,"remaining_time":0.2662635861},
{"learn":[4.408126521],"iteration":312,"passed_time":0.1209391511,"remaining_time":0.2654479131},
{"learn":[4.407843853],"iteration":313,"passed_time":0.121132987,"remaining_time":0.264640857},
{"learn":[4.405219398],"iteration":314,"passed_time":0.1213232395,"remaining_time":0.2638299019},
{"learn":[4.402708465],"iteration":315,"passed_time":0.1215062003,"remaining_time":0.2630070918},
{"learn":[4.40104971],"iteration":316,"passed_time":0.1217034946,"remaining_time":0.2622192013},
{"learn":[4.400830038],"iteration":317,"passed_time":0.1218874971,"remaining_time":0.2614065188},
{"learn":[4.39784288],"iteration":318,"passed_time":0.1220678328,"remaining_time":0.2605899502},
{"learn":[4.393741845],"iteration":319,"passed_time":0.1222572103,"remaining_time":0.2597965719},
{"learn":[4.393425936],"iteration":320,"passed_time":0.1224406294,"remaining_time":0.2589943532},
{"learn":[4.390505974],"iteration":321,"passed_time":0.1226305903,"remaining_time":0.2582097522},
{"learn":[4.390305136],"iteration":322,"passed_time":0.1228215095,"remaining_time":0.2574308419},
{"learn":[4.38568203],"iteration":323,"passed_time":0.1230129704,"remaining_time":0.2566566913},
{"learn":[4.383057135],"iteration":324,"passed_time":0.1232050563,"remaining_time":0.2558874245},
{"learn":[4.380662684],"iteration":325,"passed_time":0.123390017,"remaining_time":0.2551069678},
{"learn":[4.37805727],"iteration":326,"passed_time":0.1235899364,"remaining_time":0.2543609394},
{"learn":[4.373708319],"iteration":327,"passed_time":0.1237919391,"remaining_time":0.2536225093},
{"learn":[4.36887921],"iteration":328,"passed_time":0.1239768999,"remaining_time":0.252852583},
{"learn":[4.367895929],"iteration":329,"passed_time":0.1241685691,"remaining_time":0.2520998221},
{"learn":[4.362140573],"iteration":330,"passed_time":0.1243618633,"remaining_time":0.2513537358},
{"learn":[4.361931924],"iteration":331,"passed_time":0.1245957414,"remaining_time":0.2506926364},
{"learn":[4.359656377],"iteration":332,"passed_time":0.1248012025,"remaining_time":0.2499771834},
{"learn":[4.354281355],"iteration":333,"passed_time":0.1250019968,"remaining_time":0.2492554787},
{"learn":[4.348589447],"iteration":334,"passed_time":0.1251927494,"remaining_time":0.2485169502},
{"learn":[4.346355698],"iteration":335,"passed_time":0.1254231274,"remaining_time":0.2478599899},
{"learn":[4.343894047],"iteration":336,"passed_time":0.1256135883,"remaining_time":0.2471270298},
{"learn":[4.341561356],"iteration":337,"passed_time":0.1258037158,"remaining_time":0.2463966269},
{"learn":[4.338869061],"iteration":338,"passed_time":0.1259838849,"remaining_time":0.2456499939},
{"learn":[4.333720063],"iteration":339,"passed_time":0.1261738041,"remaining_time":0.2449256197},
{"learn":[4.330892223],"iteration":340,"passed_time":0.1263595566,"remaining_time":0.2441963278},
{"learn":[4.328311474],"iteration":341,"passed_time":0.1265867679,"remaining_time":0.2435499804},
{"learn":[4.324580133],"iteration":342,"passed_time":0.1267760204,"remaining_time":0.2428333686},
{"learn":[4.323354432],"iteration":343,"passed_time":0.1269870649,"remaining_time":0.2421613796},
{"learn":[4.323159553],"iteration":344,"passed_time":0.1271851926,"remaining_time":0.2414675395},
{"learn":[4.318639682],"iteration":345,"passed_time":0.1273865702,"remaining_time":0.2407827079},
{"learn":[4.312712208],"iteration":346,"passed_time":0.1275775728,"remaining_time":0.2400811384},
{"learn":[4.311461062],"iteration":347,"passed_time":0.1277782004,"remaining_time":0.2394005365},
{"learn":[4.311178356],"iteration":348,"passed_time":0.1279631612,"remaining_time":0.2386934612},
{"learn":[4.311102505],"iteration":349,"passed_time":0.1281452053,"remaining_time":0.2379839528},
{"learn":[4.310232308],"iteration":350,"passed_time":0.1283407496,"remaining_time":0.2373024116},
{"learn":[4.305128197],"iteration":351,"passed_time":0.1285329605,"remaining_time":0.2366174954},
{"learn":[4.304595496],"iteration":352,"passed_time":0.1287330048,"remaining_time":0.2359497284},
{"learn":[4.3004992],"iteration":353,"passed_time":0.1289396742,"remaining_time":0.2352966937},
{"learn":[4.297581524],"iteration":354,"passed_time":0.1291665939,"remaining_time":0.2346829664},
{"learn":[4.297355825],"iteration":355,"passed_time":0.1293753884,"remaining_time":0.2340386239},
{"learn":[4.295758715],"iteration":356,"passed_time":0.129572141,"remaining_time":0.2333750326},
{"learn":[4.292500657],"iteration":357,"passed_time":0.1297601435,"remaining_time":0.2326983579},
{"learn":[4.290797586],"iteration":358,"passed_time":0.1299360625,"remaining_time":0.2320028302},
{"learn":[4.286410608],"iteration":359,"passed_time":0.1301403985,"remaining_time":0.2313607085},
{"learn":[4.280278245],"iteration":360,"passed_time":0.1303256093,"remaining_time":0.2306871589},
{"learn":[4.279941283],"iteration":361,"passed_time":0.1305080701,"remaining_time":0.2300114606},
{"learn":[4.274426275],"iteration":362,"passed_time":0.1307026977,"remaining_time":0.2293598304},
{"learn":[4.273567658],"iteration":363,"passed_time":0.1309000753,"remaining_time":0.2287155162},
{"learn":[4.269488271],"iteration":364,"passed_time":0.131099078,"remaining_time":0.2280764781},
{"learn":[4.266838205],"iteration":365,"passed_time":0.1312854971,"remaining_time":0.2274180469},
{"learn":[4.263456509],"iteration":366,"passed_time":0.1314819997,"remaining_time":0.2267795799},
{"learn":[4.260360204],"iteration":367,"passed_time":0.1316720023,"remaining_time":0.2261323517},
{"learn":[4.255120549],"iteration":368,"passed_time":0.1318633798,"remaining_time":0.225489953},
{"learn":[4.252582211],"iteration":369,"passed_time":0.1320479239,"remaining_time":0.224838357},
{"learn":[4.247857931],"iteration":370,"passed_time":0.1322403848,"remaining_time":0.224202701},
{"learn":[4.245288911],"iteration":371,"passed_time":0.1324484293,"remaining_time":0.2235957354},
{"learn":[4.24048515],"iteration":372,"passed_time":0.1326486403,"remaining_time":0.2229777411},
{"learn":[4.2378365],"iteration":373,"passed_time":0.1328643098,"remaining_time":0.2223878554},
{"learn":[4.236751063],"iteration":374,"passed_time":0.1331629804,"remaining_time":0.2219383007},
{"learn":[4.233240093],"iteration":375,"passed_time":0.1333716082,"remaining_time":0.2213401158},
{"learn":[4.230358421],"iteration":376,"passed_time":0.1335621941,"remaining_time":0.2207141828},
{"learn":[4.225853583],"iteration":377,"passed_time":0.1337558217,"remaining_time":0.2200955584},
{"learn":[4.224702126],"iteration":378,"passed_time":0.1339675328,"remaining_time":0.2195088071},
{"learn":[4.224361982],"iteration":379,"passed_time":0.1341884108,"remaining_time":0.218938986},
{"learn":[4.223787954],"iteration":380,"passed_time":0.1343898718,"remaining_time":0.2183394505},
{"learn":[4.22144054],"iteration":381,"passed_time":0.1345779576,"remaining_time":0.2177203607},
{"learn":[4.217739335],"iteration":382,"passed_time":0.1347679601,"remaining_time":0.2171066094},
{"learn":[4.215611665],"iteration":383,"passed_time":0.1349517126,"remaining_time":0.2164850389},
{"learn":[4.210236863],"iteration":384,"passed_time":0.1351438818,"remaining_time":0.2158791878},
{"learn":[4.208454294],"iteration":385,"passed_time":0.1353354677,"remaining_time":0.2152745522},
{"learn":[4.207446501],"iteration":386,"passed_time":0.1355267202,"remaining_time":0.2146715233},
{"learn":[4.204985442],"iteration":387,"passed_time":0.1357120144,"remaining_time":0.2140612185},
{"learn":[4.202796622],"iteration":388,"passed_time":0.1359037669,"remaining_time":0.2134632431},
{"learn":[4.199774004],"iteration":389,"passed_time":0.1360893944,"remaining_time":0.2128577707},
{"learn":[4.199458358],"iteration":390,"passed_time":0.1362666051,"remaining_time":0.2122413363},
{"learn":[4.19751254],"iteration":391,"passed_time":0.1364840246,"remaining_time":0.2116895076},
{"learn":[4.195201346],"iteration":392,"passed_time":0.1367035692,"remaining_time":0.2111426629},
{"learn":[4.190593508],"iteration":393,"passed_time":0.1368986552,"remaining_time":0.2105598605},
{"learn":[4.187212054],"iteration":394,"passed_time":0.137088866,"remaining_time":0.2099715543},
{"learn":[4.184984466],"iteration":395,"passed_time":0.1372850353,"remaining_time":0.2093943468},
{"learn":[4.182832144],"iteration":396,"passed_time":0.1374787879,"remaining_time":0.2088153881},
{"learn":[4.179752812],"iteration":397,"passed_time":0.1376712904,"remaining_time":0.2082364745},
{"learn":[4.17878934],"iteration":398,"passed_time":0.1378584596,"remaining_time":0.2076514642},
{"learn":[4.174548229],"iteration":399,"passed_time":0.1380497121,"remaining_time":0.2070745682},
{"learn":[4.168872556],"iteration":400,"passed_time":0.1382456314,"remaining_time":0.2065065666},
{"learn":[4.163926494],"iteration":401,"passed_time":0.1384399257,"remaining_time":0.2059379989},
{"learn":[4.159485076],"iteration":402,"passed_time":0.1386340532,"remaining_time":0.2053710417},
{"learn":[4.155926102],"iteration":403,"passed_time":0.1388313892,"remaining_time":0.2048106633},
{"learn":[4.153540115],"iteration":404,"passed_time":0.1390225584,"remaining_time":0.2042430179},
{"learn":[4.150983044],"iteration":405,"passed_time":0.1392712284,"remaining_time":0.2037613539},
{"learn":[4.146539132],"iteration":406,"passed_time":0.1395248568,"remaining_time":0.2032880591},
{"learn":[4.144869174],"iteration":407,"passed_time":0.139765985,"remaining_time":0.2027977037},
{"learn":[4.142825962],"iteration":408,"passed_time":0.1399671127,"remaining_time":0.2022507667},
{"learn":[4.142467378],"iteration":409,"passed_time":0.1401535735,"remaining_time":0.2016844106},
{"learn":[4.141800768],"iteration":410,"passed_time":0.1403511178,"remaining_time":0.2011357868},
{"learn":[4.140107084],"iteration":411,"passed_time":0.1405329118,"remaining_time":0.2005663888},
{"learn":[4.136243196],"iteration":412,"passed_time":0.1407322895,"remaining_time":0.2000238594},
{"learn":[4.133618439],"iteration":413,"passed_time":0.1410176683,"remaining_time":0.1996047189},
{"learn":[4.131053025],"iteration":414,"passed_time":0.1412085458,"remaining_time":0.1990530104},
{"learn":[4.128379975],"iteration":415,"passed_time":0.1413929233,"remaining_time":0.1984939115},
{"learn":[4.127068571],"iteration":416,"passed_time":0.1415811758,"remaining_time":0.1979420276},
{"learn":[4.125969877],"iteration":417,"passed_time":0.1418284708,"remaining_time":0.1974740909},
{"learn":[4.123893633],"iteration":418,"passed_time":0.1420206816,"remaining_time":0.1969308259},
{"learn":[4.119643722],"iteration":419,"passed_time":0.1422424346,"remaining_time":0.1964300287},
{"learn":[4.11465686],"iteration":420,"passed_time":0.1424371455,"remaining_time":0.1958933664},
{"learn":[4.111565986],"iteration":421,"passed_time":0.1426275231,"remaining_time":0.1953523894},
{"learn":[4.106322452],"iteration":422,"passed_time":0.1428249007,"remaining_time":0.1948226187},
{"learn":[4.104222175],"iteration":423,"passed_time":0.1430163616,"remaining_time":0.194286378},
{"learn":[4.103008002],"iteration":424,"passed_time":0.1432022807,"remaining_time":0.1937442621},
{"learn":[4.099176337],"iteration":425,"passed_time":0.143403075,"remaining_time":0.1932238617},
{"learn":[4.096525716],"iteration":426,"passed_time":0.1435925776,"remaining_time":0.1926898055},
{"learn":[4.094967724],"iteration":427,"passed_time":0.143825289,"remaining_time":0.1922151059},
{"learn":[4.094683584],"iteration":428,"passed_time":0.1440552504,"remaining_time":0.1917378741},
{"learn":[4.091096563],"iteration":429,"passed_time":0.1442392945,"remaining_time":0.1912009253},
{"learn":[4.089178677],"iteration":430,"passed_time":0.1444514223,"remaining_time":0.1907026898},
{"learn":[4.085335077],"iteration":431,"passed_time":0.1446473833,"remaining_time":0.1901845224},
{"learn":[4.084852122],"iteration":432,"passed_time":0.1448529277,"remaining_time":0.1896803926},
{"learn":[4.080322952],"iteration":433,"passed_time":0.1450435969,"remaining_time":0.1891582392},
{"learn":[4.077449519],"iteration":434,"passed_time":0.1452323077,"remaining_time":0.1886350663},
{"learn":[4.076568374],"iteration":435,"passed_time":0.1454173102,"remaining_time":0.1881086306},
{"learn":[4.076071793],"iteration":436,"passed_time":0.1456076044,"remaining_time":0.187590575},
{"learn":[4.075027644],"iteration":437,"passed_time":0.1458045237,"remaining_time":0.1870825167},
{"learn":[4.07020837],"iteration":438,"passed_time":0.1460017346,"remaining_time":0.1865762486},
{"learn":[4.06833694],"iteration":439,"passed_time":0.1461892788,"remaining_time":0.1860590821},
{"learn":[4.063936568],"iteration":440,"passed_time":0.1464048233,"remaining_time":0.185578903},
{"learn":[4.061734926],"iteration":441,"passed_time":0.1466027843,"remaining_time":0.1850777232},
{"learn":[4.060815619],"iteration":442,"passed_time":0.146803662,"remaining_time":0.1845815795},
{"learn":[4.056407489],"iteration":443,"passed_time":0.1470058313,"remaining_time":0.1840883834},
{"learn":[4.05238936],"iteration":444,"passed_time":0.1472091674,"remaining_time":0.1835979503},
{"learn":[4.049685254],"iteration":445,"passed_time":0.1474033366,"remaining_time":0.1830974181},
{"learn":[4.045162016],"iteration":446,"passed_time":0.1476044643,"remaining_time":0.1826068652},
{"learn":[4.042955482],"iteration":447,"passed_time":0.1477850084,"remaining_time":0.1820922424},
{"learn":[4.041467663],"iteration":448,"passed_time":0.1479868444,"remaining_time":0.1816052366},
{"learn":[4.038920476],"iteration":449,"passed_time":0.148181597,"remaining_time":0.1811108407},
{"learn":[4.036694383],"iteration":450,"passed_time":0.1483787663,"remaining_time":0.1806207155},
{"learn":[4.034999007],"iteration":451,"passed_time":0.1485706021,"remaining_time":0.1801254203},
{"learn":[4.031928018],"iteration":452,"passed_time":0.148858606,"remaining_time":0.1797475882},
{"learn":[4.028718143],"iteration":453,"passed_time":0.1490630254,"remaining_time":0.1792696296},
{"learn":[4.027401978],"iteration":454,"passed_time":0.1493536959,"remaining_time":0.1788961852},
{"learn":[4.025930598],"iteration":455,"passed_time":0.1495604487,"remaining_time":0.1784229914},
{"learn":[4.021074523],"iteration":456,"passed_time":0.1497517845,"remaining_time":0.1779326455},
{"learn":[4.020268486],"iteration":457,"passed_time":0.1499487455,"remaining_time":0.1774502621},
{"learn":[4.017986361],"iteration":458,"passed_time":0.1501395397,"remaining_time":0.176961854},
{"learn":[4.014814804],"iteration":459,"passed_time":0.1503388757,"remaining_time":0.1764847671},
{"learn":[4.009704796],"iteration":460,"passed_time":0.1505333783,"remaining_time":0.176003234},
{"learn":[4.008440457],"iteration":461,"passed_time":0.1507462144,"remaining_time":0.175544293},
{"learn":[4.004854849],"iteration":462,"passed_time":0.1509376753,"remaining_time":0.1750616234},
{"learn":[4.000898028],"iteration":463,"passed_time":0.1511225944,"remaining_time":0.1745726522},
{"learn":[3.996617985],"iteration":464,"passed_time":0.1513079719,"remaining_time":0.1740855161},
{"learn":[3.995443319],"iteration":465,"passed_time":0.1515092246,"remaining_time":0.1736178668},
{"learn":[3.990771995],"iteration":466,"passed_time":0.1517058522,"remaining_time":0.1731460797},
{"learn":[3.989249359],"iteration":467,"passed_time":0.1518946047,"remaining_time":0.1726665165},
{"learn":[3.986599538],"iteration":468,"passed_time":0.1520911907,"remaining_time":0.1721970623},
{"learn":[3.985628919],"iteration":469,"passed_time":0.1522792348,"remaining_time":0.1717191372},
{"learn":[3.985086112],"iteration":470,"passed_time":0.1524646123,"remaining_time":0.1712394478},
{"learn":[3.98466839],"iteration":471,"passed_time":0.1526555732,"remaining_time":0.1707672513},
{"learn":[3.984233894],"iteration":472,"passed_time":0.1528477424,"remaining_time":0.1702975904},
{"learn":[3.981855845],"iteration":473,"passed_time":0.1530495367,"remaining_time":0.1698397813},
{"learn":[3.978684264],"iteration":474,"passed_time":0.1532433727,"remaining_time":0.169374254},
{"learn":[3.974361269],"iteration":475,"passed_time":0.1534433753,"remaining_time":0.1689166569},
{"learn":[3.972074049],"iteration":476,"passed_time":0.1536332529,"remaining_time":0.1684490382},
{"learn":[3.97191982],"iteration":477,"passed_time":0.1538267554,"remaining_time":0.1679865404},
{"learn":[3.969616848],"iteration":478,"passed_time":0.1540222164,"remaining_time":0.1675272959},
{"learn":[3.968533527],"iteration":479,"passed_time":0.1542265107,"remaining_time":0.16707872},
{"learn":[3.967568753],"iteration":480,"passed_time":0.1544176383,"remaining_time":0.1666169527},
{"learn":[3.966232553],"iteration":481,"passed_time":0.1546080992,"remaining_time":0.166155592},
{"learn":[3.961522393],"iteration":482,"passed_time":0.1548112685,"remaining_time":0.1657089562},
{"learn":[3.955829553],"iteration":483,"passed_time":0.1550040628,"remaining_time":0.1652522653},
{"learn":[3.954248095],"iteration":484,"passed_time":0.1551980653,"remaining_time":0.1647979457},
{"learn":[3.951922606],"iteration":485,"passed_time":0.155394068,"remaining_time":0.1643468126},
{"learn":[3.94978202],"iteration":486,"passed_time":0.1556044458,"remaining_time":0.16391187},
{"learn":[3.949518999],"iteration":487,"passed_time":0.1557929483,"remaining_time":0.1634548965},
{"learn":[3.945431216],"iteration":488,"passed_time":0.1559857842,"remaining_time":0.1630035495},
{"learn":[3.943249086],"iteration":489,"passed_time":0.1561624115,"remaining_time":0.1625363875},
{"learn":[3.941981548],"iteration":490,"passed_time":0.1563413306,"remaining_time":0.1620727846},
{"learn":[3.936600517],"iteration":491,"passed_time":0.1565520417,"remaining_time":0.161643165},
{"learn":[3.934476885],"iteration":492,"passed_time":0.156751086,"remaining_time":0.1612024353},
{"learn":[3.93045798],"iteration":493,"passed_time":0.1569202133,"remaining_time":0.1607320403},
{"learn":[3.925977375],"iteration":494,"passed_time":0.1571422162,"remaining_time":0.1603168064},
{"learn":[3.92457993],"iteration":495,"passed_time":0.1573254687,"remaining_time":0.1598629762},
{"learn":[3.919849146],"iteration":496,"passed_time":0.1575236796,"remaining_time":0.1594253739},
{"learn":[3.919681964],"iteration":497,"passed_time":0.1577160155,"remaining_time":0.1589828108},
{"learn":[3.917633027],"iteration":498,"passed_time":0.1579099348,"remaining_time":0.1585428403},
{"learn":[3.916616419],"iteration":499,"passed_time":0.1581078124,"remaining_time":0.1581078124},
{"learn":[3.912896166],"iteration":500,"passed_time":0.1582959399,"remaining_time":0.15766402},
{"learn":[3.912769674],"iteration":501,"passed_time":0.1584821924,"remaining_time":0.1572193861},
{"learn":[3.909373788],"iteration":502,"passed_time":0.158679695,"remaining_time":0.1567868955},
{"learn":[3.906706036],"iteration":503,"passed_time":0.1588645308,"remaining_time":0.1563428716},
{"learn":[3.903895664],"iteration":504,"passed_time":0.1590601167,"remaining_time":0.1559104115},
{"learn":[3.902982967],"iteration":505,"passed_time":0.1592677445,"remaining_time":0.1554906438},
{"learn":[3.900905528],"iteration":506,"passed_time":0.1594588304,"remaining_time":0.155055628},
{"learn":[3.897463465],"iteration":507,"passed_time":0.1596404578,"remaining_time":0.1546124119},
{"learn":[3.895918033],"iteration":508,"passed_time":0.1598394604,"remaining_time":0.1541869844},
{"learn":[3.893921936],"iteration":509,"passed_time":0.160030463,"remaining_time":0.1537547586},
{"learn":[3.890237934],"iteration":510,"passed_time":0.1602223405,"remaining_time":0.1533243141},
{"learn":[3.887311613],"iteration":511,"passed_time":0.1604150931,"remaining_time":0.1528956356},
{"learn":[3.884869735],"iteration":512,"passed_time":0.1606566797,"remaining_time":0.1525142358},
{"learn":[3.882101231],"iteration":513,"passed_time":0.160857349,"remaining_time":0.1520946918},
{"learn":[3.88060368],"iteration":514,"passed_time":0.1610488932,"remaining_time":0.1516674043},
{"learn":[3.877726076],"iteration":515,"passed_time":0.161236979,"remaining_time":0.1512377865},
{"learn":[3.874938145],"iteration":516,"passed_time":0.1614265232,"remaining_time":0.1508104656},
{"learn":[3.874340833],"iteration":517,"passed_time":0.161631026,"remaining_time":0.1503979817},
{"learn":[3.873105224],"iteration":518,"passed_time":0.1618155284,"remaining_time":0.1499677633},
{"learn":[3.869800236],"iteration":519,"passed_time":0.1620128644,"remaining_time":0.1495503363},
{"learn":[3.867932518],"iteration":520,"passed_time":0.1621928668,"remaining_time":0.149117818},
{"learn":[3.866666962],"iteration":521,"passed_time":0.1623848276,"remaining_time":0.1486972177},
{"learn":[3.865527652],"iteration":522,"passed_time":0.1625781636,"remaining_time":0.1482787457},
{"learn":[3.861900081],"iteration":523,"passed_time":0.1627609577,"remaining_time":0.147851557},
{"learn":[3.858502887],"iteration":524,"passed_time":0.1629791689,"remaining_time":0.1474573433},
{"learn":[3.858335097],"iteration":525,"passed_time":0.1631735048,"remaining_time":0.1470422838},
{"learn":[3.855719306],"iteration":526,"passed_time":0.1633736741,"remaining_time":0.1466332977},
{"learn":[3.855137428],"iteration":527,"passed_time":0.1635703434,"remaining_time":0.1462219737},
{"learn":[3.851985706],"iteration":528,"passed_time":0.1637740961,"remaining_time":0.145817768},
{"learn":[3.851051809],"iteration":529,"passed_time":0.1639534735,"remaining_time":0.1453927029},
{"learn":[3.850679146],"iteration":530,"passed_time":0.1641891433,"remaining_time":0.1450182829},
{"learn":[3.848179484],"iteration":531,"passed_time":0.1644406467,"remaining_time":0.1446583132},
{"learn":[3.844551071],"iteration":532,"passed_time":0.1646456911,"remaining_time":0.1442580445},
{"learn":[3.841604794],"iteration":533,"passed_time":0.1648601523,"remaining_time":0.1438667246},
{"learn":[3.83969656],"iteration":534,"passed_time":0.1650539882,"remaining_time":0.1434581392},
{"learn":[3.836811463],"iteration":535,"passed_time":0.1652254488,"remaining_time":0.1430309855},
{"learn":[3.834182551],"iteration":536,"passed_time":0.1654301598,"remaining_time":0.1426334525},
{"learn":[3.828012842],"iteration":537,"passed_time":0.1656271208,"remaining_time":0.1422299811},
{"learn":[3.826636176],"iteration":538,"passed_time":0.1658250401,"remaining_time":0.1418280955},
{"learn":[3.826189798],"iteration":539,"passed_time":0.1660057092,"remaining_time":0.1414122708},
{"learn":[3.824104738],"iteration":540,"passed_time":0.1662120869,"remaining_time":0.1410191273},
{"learn":[3.82300218],"iteration":541,"passed_time":0.1663915476,"remaining_time":0.1406039277},
{"learn":[3.817146402],"iteration":542,"passed_time":0.1665878836,"remaining_time":0.1402037989},
{"learn":[3.814638044],"iteration":543,"passed_time":0.1667766778,"remaining_time":0.1397980975},
{"learn":[3.812979573],"iteration":544,"passed_time":0.1669838889,"remaining_time":0.1394085678},
{"learn":[3.811938825],"iteration":545,"passed_time":0.1671685163,"remaining_time":0.1390009275},
{"learn":[3.811479418],"iteration":546,"passed_time":0.1673538938,"remaining_time":0.1385947237},
{"learn":[3.80742981],"iteration":547,"passed_time":0.1675308545,"remaining_time":0.1381823836},
{"learn":[3.805097043],"iteration":548,"passed_time":0.1677159403,"remaining_time":0.1377775757},
{"learn":[3.801577232],"iteration":549,"passed_time":0.1679101512,"remaining_time":0.1373810328},
{"learn":[3.799762083],"iteration":550,"passed_time":0.1681049871,"remaining_time":0.1369857336},
{"learn":[3.796393455],"iteration":551,"passed_time":0.1682937396,"remaining_time":0.1365862235},
{"learn":[3.793486459],"iteration":552,"passed_time":0.1684894922,"remaining_time":0.1361931339},
{"learn":[3.792006091],"iteration":553,"passed_time":0.1686726613,"remaining_time":0.1357906263},
{"learn":[3.78932128],"iteration":554,"passed_time":0.1688574555,"remaining_time":0.135390212},
{"learn":[3.787581812],"iteration":555,"passed_time":0.1690620415,"remaining_time":0.1350063785},
{"learn":[3.785308865],"iteration":556,"passed_time":0.1692672526,"remaining_time":0.1346236856},
{"learn":[3.78465475],"iteration":557,"passed_time":0.1694480883,"remaining_time":0.1342223208},
{"learn":[3.780498869],"iteration":558,"passed_time":0.1696436742,"remaining_time":0.1338333817},
{"learn":[3.778734909],"iteration":559,"passed_time":0.1698356768,"remaining_time":0.1334423175},
{"learn":[3.778652349],"iteration":560,"passed_time":0.170022346,"remaining_time":0.1330477894},
{"learn":[3.777928006],"iteration":561,"passed_time":0.1702179736,"remaining_time":0.132660983},
{"learn":[3.776131406],"iteration":562,"passed_time":0.1704106011,"remaining_time":0.132272527},
{"learn":[3.772925617],"iteration":563,"passed_time":0.1706078954,"remaining_time":0.131888373},
{"learn":[3.7727745],"iteration":564,"passed_time":0.1707795227,"remaining_time":0.1314851192},
{"learn":[3.771763073],"iteration":565,"passed_time":0.1709769003,"remaining_time":0.1311024289},
{"learn":[3.768738162],"iteration":566,"passed_time":0.1712050284,"remaining_time":0.1307438753},
{"learn":[3.767220794],"iteration":567,"passed_time":0.1714276563,"remaining_time":0.1303815978},
{"learn":[3.766691102],"iteration":568,"passed_time":0.1716423258,"remaining_time":0.1300137828},
{"learn":[3.766259335],"iteration":569,"passed_time":0.1718374118,"remaining_time":0.1296317317},
{"learn":[3.76116362],"iteration":570,"passed_time":0.1720252059,"remaining_time":0.129244857},
{"learn":[3.758633056],"iteration":571,"passed_time":0.1722045,"remaining_time":0.1288523182},
{"learn":[3.754603809],"iteration":572,"passed_time":0.1723764606,"remaining_time":0.1284550588},
{"learn":[3.754070549],"iteration":573,"passed_time":0.1725779633,"remaining_time":0.1280805093},
{"learn":[3.750534319],"iteration":574,"passed_time":0.1727623408,"remaining_time":0.127693904},
{"learn":[3.746491516],"iteration":575,"passed_time":0.1729549266,"remaining_time":0.1273140432},
{"learn":[3.744210544],"iteration":576,"passed_time":0.1731379291,"remaining_time":0.1269278059},
{"learn":[3.742929991],"iteration":577,"passed_time":0.1733101814,"remaining_time":0.1265344231},
{"learn":[3.740402992],"iteration":578,"passed_time":0.1735518513,"remaining_time":0.1261922787},
{"learn":[3.739644243],"iteration":579,"passed_time":0.1737925211,"remaining_time":0.1258497567},
{"learn":[3.737529404],"iteration":580,"passed_time":0.1740133574,"remaining_time":0.1254932818},
{"learn":[3.737196923],"iteration":581,"passed_time":0.1742152351,"remaining_time":0.1251236568},
{"learn":[3.733954464],"iteration":582,"passed_time":0.1744112377,"remaining_time":0.124750405},
{"learn":[3.731608623],"iteration":583,"passed_time":0.174610032,"remaining_time":0.1243797488},
{"learn":[3.729843952],"iteration":584,"passed_time":0.1748002429,"remaining_time":0.1240035911},
{"learn":[3.727223798],"iteration":585,"passed_time":0.1749916621,"remaining_time":0.1236289217},
{"learn":[3.725351667],"iteration":586,"passed_time":0.17521179,"remaining_time":0.1232750754},
{"learn":[3.725026912],"iteration":587,"passed_time":0.1753996675,"remaining_time":0.1228990868},
{"learn":[3.721974565],"iteration":588,"passed_time":0.1755832116,"remaining_time":0.122520713},
{"learn":[3.720269493],"iteration":589,"passed_time":0.1757773809,"remaining_time":0.1221503833},
{"learn":[3.718907466],"iteration":590,"passed_time":0.1759651334,"remaining_time":0.1217762091},
{"learn":[3.715602912],"iteration":591,"passed_time":0.1761671777,"remaining_time":0.1214125144},
{"learn":[3.714463059],"iteration":592,"passed_time":0.1763565136,"remaining_time":0.1210406425},
{"learn":[3.710802077],"iteration":593,"passed_time":0.1765510995,"remaining_time":0.1206729737},
{"learn":[3.708032435],"iteration":594,"passed_time":0.1767353103,"remaining_time":0.1202988247},
{"learn":[3.703788939],"iteration":595,"passed_time":0.1769345629,"remaining_time":0.1199355091},
{"learn":[3.702500944],"iteration":596,"passed_time":0.1771241488,"remaining_time":0.1195662177},
{"learn":[3.698196925],"iteration":597,"passed_time":0.1773144847,"remaining_time":0.1191980315},
{"learn":[3.69658891],"iteration":598,"passed_time":0.1775091539,"remaining_time":0.1188333401},
{"learn":[3.696124066],"iteration":599,"passed_time":0.1777045732,"remaining_time":0.1184697155},
{"learn":[3.693537052],"iteration":600,"passed_time":0.177888034,"remaining_time":0.1180987114},
{"learn":[3.691343275],"iteration":601,"passed_time":0.178119287,"remaining_time":0.1177599273},
{"learn":[3.690973831],"iteration":602,"passed_time":0.1783259148,"remaining_time":0.1174052872},
{"learn":[3.686151073],"iteration":603,"passed_time":0.1785091256,"remaining_time":0.1170357843},
{"learn":[3.683921982],"iteration":604,"passed_time":0.1786977947,"remaining_time":0.116670461},
{"learn":[3.679975271],"iteration":605,"passed_time":0.1788921723,"remaining_time":0.1163094322},
{"learn":[3.674047638],"iteration":606,"passed_time":0.1790905083,"remaining_time":0.1159515153},
{"learn":[3.673151794],"iteration":607,"passed_time":0.1792997194,"remaining_time":0.1156011349},
{"learn":[3.670953108],"iteration":608,"passed_time":0.1795100555,"remaining_time":0.1152519404},
{"learn":[3.6703947],"iteration":609,"passed_time":0.1797012248,"remaining_time":0.114890947},
{"learn":[3.668433805],"iteration":610,"passed_time":0.1799222694,"remaining_time":0.1145495299},
{"learn":[3.668304956],"iteration":611,"passed_time":0.1801544808,"remaining_time":0.1142155859},
{"learn":[3.667880012],"iteration":612,"passed_time":0.1803541084,"remaining_time":0.1138614029},
{"learn":[3.667282264],"iteration":613,"passed_time":0.1805418609,"remaining_time":0.1135002579},
{"learn":[3.664611483],"iteration":614,"passed_time":0.1807389469,"remaining_time":0.1131455196},
{"learn":[3.662543394],"iteration":615,"passed_time":0.1809310328,"remaining_time":0.1127881763},
{"learn":[3.659041959],"iteration":616,"passed_time":0.1811283688,"remaining_time":0.1124346276},
{"learn":[3.656868545],"iteration":617,"passed_time":0.181345955,"remaining_time":0.1120941016},
{"learn":[3.654785614],"iteration":618,"passed_time":0.1815551244,"remaining_time":0.1117487923},
{"learn":[3.654566096],"iteration":619,"passed_time":0.1817981693,"remaining_time":0.1114246844},
{"learn":[3.651007045],"iteration":620,"passed_time":0.182002422,"remaining_time":0.1110771626},
{"learn":[3.648921786],"iteration":621,"passed_time":0.1822069664,"remaining_time":0.1107302786},
{"learn":[3.647655706],"iteration":622,"passed_time":0.182396844,"remaining_time":0.1103749762},
{"learn":[3.647241144],"iteration":623,"passed_time":0.1825798464,"remaining_time":0.1100160613},
{"learn":[3.644195689],"iteration":624,"passed_time":0.1827765157,"remaining_time":0.1096659094},
{"learn":[3.642632246],"iteration":625,"passed_time":0.1829888518,"remaining_time":0.109325608},
{"learn":[3.642523322],"iteration":626,"passed_time":0.1831209786,"remaining_time":0.1089379984},
{"learn":[3.641494659],"iteration":627,"passed_time":0.1833135645,"remaining_time":0.1085870159},
{"learn":[3.63976496],"iteration":628,"passed_time":0.1835084421,"remaining_time":0.1082378887},
{"learn":[3.637945652],"iteration":629,"passed_time":0.1837139865,"remaining_time":0.1078955159},
{"learn":[3.636233667],"iteration":630,"passed_time":0.1839090308,"remaining_time":0.1075474364},
{"learn":[3.635304404],"iteration":631,"passed_time":0.1841197002,"remaining_time":0.1072089394},
{"learn":[3.632234951],"iteration":632,"passed_time":0.1843146195,"remaining_time":0.1068617146},
{"learn":[3.631630987],"iteration":633,"passed_time":0.1845205389,"remaining_time":0.1065213206},
{"learn":[3.630301009],"iteration":634,"passed_time":0.1847128748,"remaining_time":0.1061735422},
{"learn":[3.629077964],"iteration":635,"passed_time":0.1848894188,"remaining_time":0.1058172145},
{"learn":[3.628004522],"iteration":636,"passed_time":0.1850739629,"remaining_time":0.1054660103},
{"learn":[3.625062876],"iteration":637,"passed_time":0.185283799,"remaining_time":0.1051296791},
{"learn":[3.624917986],"iteration":638,"passed_time":0.1854715099,"remaining_time":0.1047812442},
{"learn":[3.622887087],"iteration":639,"passed_time":0.1856620958,"remaining_time":0.1044349289},
{"learn":[3.621220865],"iteration":640,"passed_time":0.1858529733,"remaining_time":0.1040892627},
{"learn":[3.621143844],"iteration":641,"passed_time":0.1860445592,"remaining_time":0.1037444738},
{"learn":[3.620822821],"iteration":642,"passed_time":0.18623527,"remaining_time":0.1033996756},
{"learn":[3.619202826],"iteration":643,"passed_time":0.1864378561,"remaining_time":0.1030619204},
{"learn":[3.618204882],"iteration":644,"passed_time":0.1866714842,"remaining_time":0.1027416696},
{"learn":[3.614259666],"iteration":645,"passed_time":0.1868458198,"remaining_time":0.1023891954},
{"learn":[3.613415661],"iteration":646,"passed_time":0.1870375724,"remaining_time":0.1020467744},
{"learn":[3.611096773],"iteration":647,"passed_time":0.1872275332,"remaining_time":0.1017038452},
{"learn":[3.610820695],"iteration":648,"passed_time":0.1873985772,"remaining_time":0.1013511565},
{"learn":[3.609290065],"iteration":649,"passed_time":0.187561746,"remaining_time":0.1009947863},
{"learn":[3.60897947],"iteration":650,"passed_time":0.1877389984,"remaining_time":0.1006465598},
{"learn":[3.606570702],"iteration":651,"passed_time":0.1879147507,"remaining_time":0.1002980571},
{"learn":[3.606292637],"iteration":652,"passed_time":0.1881541706,"remaining_time":0.09998391607},
{"learn":[3.602753838],"iteration":653,"passed_time":0.1883514232,"remaining_time":0.09964769485},
{"learn":[3.599755869],"iteration":654,"passed_time":0.1885505092,"remaining_time":0.09931286362},
{"learn":[3.599509575],"iteration":655,"passed_time":0.1887425951,"remaining_time":0.09897477547},
{"learn":[3.595337722],"iteration":656,"passed_time":0.1889479311,"remaining_time":0.09864404929},
{"learn":[3.595168561],"iteration":657,"passed_time":0.1891550172,"remaining_time":0.09831461382},
{"learn":[3.59290559],"iteration":658,"passed_time":0.1893550199,"remaining_time":0.09798188435},
{"learn":[3.592015928],"iteration":659,"passed_time":0.1895623977,"remaining_time":0.09765335637},
{"learn":[3.590680403],"iteration":660,"passed_time":0.1897425251,"remaining_time":0.09731121935},
{"learn":[3.590361532],"iteration":661,"passed_time":0.1899176524,"remaining_time":0.09696701889},
{"learn":[3.589069739],"iteration":662,"passed_time":0.190139697,"remaining_time":0.09664717631},
{"learn":[3.585010186],"iteration":663,"passed_time":0.190336158,"remaining_time":0.09631468234},
{"learn":[3.582997552],"iteration":664,"passed_time":0.1905130353,"remaining_time":0.09597273207},
{"learn":[3.582119256],"iteration":665,"passed_time":0.1906782042,"remaining_time":0.0956254057},
{"learn":[3.579019356],"iteration":666,"passed_time":0.1908454147,"remaining_time":0.09527964483},
{"learn":[3.57719559],"iteration":667,"passed_time":0.1910117919,"remaining_time":0.09493400438},
{"learn":[3.574050046],"iteration":668,"passed_time":0.1911863776,"remaining_time":0.09459296111},
{"learn":[3.572204518],"iteration":669,"passed_time":0.191417589,"remaining_time":0.09428030503},
{"learn":[3.569508025],"iteration":670,"passed_time":0.1916322169,"remaining_time":0.09395976058},
{"learn":[3.566268704],"iteration":671,"passed_time":0.1918521365,"remaining_time":0.09364211422},
{"learn":[3.562564052],"iteration":672,"passed_time":0.1920596392,"remaining_time":0.09331872515},
{"learn":[3.561173586],"iteration":673,"passed_time":0.192243225,"remaining_time":0.09298411179},
{"learn":[3.559551904],"iteration":674,"passed_time":0.1924472277,"remaining_time":0.09265977631},
{"learn":[3.558593054],"iteration":675,"passed_time":0.1926285635,"remaining_time":0.09232493278},
{"learn":[3.555647008],"iteration":676,"passed_time":0.1928735667,"remaining_time":0.09202091883},
{"learn":[3.553100059],"iteration":677,"passed_time":0.193072986,"remaining_time":0.09169542995},
{"learn":[3.55085578],"iteration":678,"passed_time":0.1932623636,"remaining_time":0.0913655651},
{"learn":[3.550737965],"iteration":679,"passed_time":0.1934631579,"remaining_time":0.09104148607},
{"learn":[3.549408772],"iteration":680,"passed_time":0.1936944943,"remaining_time":0.0907320759},
{"learn":[3.547390589],"iteration":681,"passed_time":0.1938946636,"remaining_time":0.09040836223},
{"learn":[3.54723575],"iteration":682,"passed_time":0.1940766244,"remaining_time":0.0900765592},
{"learn":[3.543988891],"iteration":683,"passed_time":0.194271752,"remaining_time":0.08975127724},
{"learn":[3.543868508],"iteration":684,"passed_time":0.1944657546,"remaining_time":0.08942585794},
{"learn":[3.542752124],"iteration":685,"passed_time":0.1946595072,"remaining_time":0.08910070736},
{"learn":[3.541334315],"iteration":686,"passed_time":0.1948687599,"remaining_time":0.08878300125},
{"learn":[3.540208266],"iteration":687,"passed_time":0.1950498457,"remaining_time":0.08845283699},
{"learn":[3.537730983],"iteration":688,"passed_time":0.1952376398,"remaining_time":0.08812613352},
{"learn":[3.53419867],"iteration":689,"passed_time":0.195426184,"remaining_time":0.08780016963},
{"learn":[3.532628335],"iteration":690,"passed_time":0.1957019377,"remaining_time":0.08751360166},
{"learn":[3.532204987],"iteration":691,"passed_time":0.1959205656,"remaining_time":0.08720163902},
{"learn":[3.530618147],"iteration":692,"passed_time":0.1961046514,"remaining_time":0.08687464354},
{"learn":[3.528909306],"iteration":693,"passed_time":0.1962876538,"remaining_time":0.08654758223},
{"learn":[3.526700678],"iteration":694,"passed_time":0.1964863648,"remaining_time":0.08622782916},
{"learn":[3.526439574],"iteration":695,"passed_time":0.1966920342,"remaining_time":0.08591146321},
{"learn":[3.525784216],"iteration":696,"passed_time":0.1968950369,"remaining_time":0.08559425564},
{"learn":[3.524112693],"iteration":697,"passed_time":0.1970792477,"remaining_time":0.0852692447},
{"learn":[3.522813541],"iteration":698,"passed_time":0.1972947922,"remaining_time":0.08495812941},
{"learn":[3.519148203],"iteration":699,"passed_time":0.1975292537,"remaining_time":0.08465539443},
{"learn":[3.517236747],"iteration":700,"passed_time":0.1977357564,"remaining_time":0.08434092892},
{"learn":[3.515603888],"iteration":701,"passed_time":0.1979430508,"remaining_time":0.08402710706},
{"learn":[3.51263524],"iteration":702,"passed_time":0.1981660122,"remaining_time":0.08372020712},
{"learn":[3.51123442],"iteration":703,"passed_time":0.1983678898,"remaining_time":0.08340468095},
{"learn":[3.50828027],"iteration":704,"passed_time":0.1985682258,"remaining_time":0.08308883209},
{"learn":[3.508265537],"iteration":705,"passed_time":0.1986607687,"remaining_time":0.08272842211},
{"learn":[3.506774876],"iteration":706,"passed_time":0.198856063,"remaining_time":0.08241135284},
{"learn":[3.50552068],"iteration":707,"passed_time":0.1990458155,"remaining_time":0.082092342},
{"learn":[3.501973993],"iteration":708,"passed_time":0.1992467765,"remaining_time":0.08177829615},
{"learn":[3.498880354],"iteration":709,"passed_time":0.1994418208,"remaining_time":0.08146215216},
{"learn":[3.497370959],"iteration":710,"passed_time":0.1996266566,"remaining_time":0.08114219937},
{"learn":[3.496050455],"iteration":711,"passed_time":0.1998085757,"remaining_time":0.08082144634},
{"learn":[3.495630067],"iteration":712,"passed_time":0.2000034116,"remaining_time":0.08050628209},
{"learn":[3.49550669],"iteration":713,"passed_time":0.2001913724,"remaining_time":0.080188701},
{"learn":[3.493652375],"iteration":714,"passed_time":0.2003999585,"remaining_time":0.07987970376},
{"learn":[3.491915684],"iteration":715,"passed_time":0.2006015862,"remaining_time":0.07956822694},
{"learn":[3.490303956],"iteration":716,"passed_time":0.200786422,"remaining_time":0.07925042878},
{"learn":[3.488363853],"iteration":717,"passed_time":0.2010003415,"remaining_time":0.07894442383},
{"learn":[3.485483936],"iteration":718,"passed_time":0.2011938441,"remaining_time":0.07863069568},
{"learn":[3.483763466],"iteration":719,"passed_time":0.2013809299,"remaining_time":0.07831480609},
{"learn":[3.481642352],"iteration":720,"passed_time":0.2015805159,"remaining_time":0.07800411088},
{"learn":[3.479826119],"iteration":721,"passed_time":0.2017854353,"remaining_time":0.07769577703},
{"learn":[3.478588728],"iteration":722,"passed_time":0.201989563,"remaining_time":0.07738742595},
{"learn":[3.475390887],"iteration":723,"passed_time":0.2021854823,"remaining_time":0.07707623359},
{"learn":[3.472636852],"iteration":724,"passed_time":0.2023716515,"remaining_time":0.0767616609},
{"learn":[3.47061883],"iteration":725,"passed_time":0.2026296549,"remaining_time":0.07647455295},
{"learn":[3.46953149],"iteration":726,"passed_time":0.2028318242,"remaining_time":0.07616655848},
{"learn":[3.467217162],"iteration":727,"passed_time":0.2030826609,"remaining_time":0.07587703814},
{"learn":[3.465686216],"iteration":728,"passed_time":0.2032732051,"remaining_time":0.07556521068},
{"learn":[3.462631216],"iteration":729,"passed_time":0.2034644993,"remaining_time":0.0752539929},
{"learn":[3.461451053],"iteration":730,"passed_time":0.2036630853,"remaining_time":0.07494578652},
{"learn":[3.458950469],"iteration":731,"passed_time":0.2038462544,"remaining_time":0.07463223522},
{"learn":[3.458072145],"iteration":732,"passed_time":0.2040474238,"remaining_time":0.07432559637},
{"learn":[3.454364268],"iteration":733,"passed_time":0.2042742184,"remaining_time":0.07402853148},
{"learn":[3.453243406],"iteration":734,"passed_time":0.2044703877,"remaining_time":0.07372061598},
{"learn":[3.453017963],"iteration":735,"passed_time":0.2046647653,"remaining_time":0.07341236147},
{"learn":[3.45201581],"iteration":736,"passed_time":0.2048753931,"remaining_time":0.07311021491},
{"learn":[3.449510107],"iteration":737,"passed_time":0.2050637289,"remaining_time":0.07280040242},
{"learn":[3.447189189],"iteration":738,"passed_time":0.2052608566,"remaining_time":0.07249402377},
{"learn":[3.446423605],"iteration":739,"passed_time":0.2054486507,"remaining_time":0.07218466107},
{"learn":[3.445531987],"iteration":740,"passed_time":0.2056639869,"remaining_time":0.07188525319},
{"learn":[3.445328199],"iteration":741,"passed_time":0.2058800315,"remaining_time":0.07158631822},
{"learn":[3.443327544],"iteration":742,"passed_time":0.2060653256,"remaining_time":0.07127696996},
{"learn":[3.441475798],"iteration":743,"passed_time":0.206269995,"remaining_time":0.07097462193},
{"learn":[3.439046501],"iteration":744,"passed_time":0.2064572058,"remaining_time":0.07066656038},
{"learn":[3.435899469],"iteration":745,"passed_time":0.2066334998,"remaining_time":0.07035510584},
{"learn":[3.433988352],"iteration":746,"passed_time":0.2068164606,"remaining_time":0.07004627113},
{"learn":[3.433413263],"iteration":747,"passed_time":0.2070014214,"remaining_time":0.06973844678},
{"learn":[3.429944699],"iteration":748,"passed_time":0.2072079241,"remaining_time":0.06943816951},
{"learn":[3.429291634],"iteration":749,"passed_time":0.2073871349,"remaining_time":0.06912904495},
{"learn":[3.429175603],"iteration":750,"passed_time":0.2075675123,"remaining_time":0.0688206532},
{"learn":[3.428780323],"iteration":751,"passed_time":0.2077637649,"remaining_time":0.06851783735},
{"learn":[3.423893341],"iteration":752,"passed_time":0.2079556424,"remaining_time":0.06821386943},
{"learn":[3.421024316],"iteration":753,"passed_time":0.2081813538,"remaining_time":0.06792123744},
{"learn":[3.420969872],"iteration":754,"passed_time":0.2084697743,"remaining_time":0.06764913205},
{"learn":[3.419544785],"iteration":755,"passed_time":0.2093613278,"remaining_time":0.06757164548},
{"learn":[3.417057977],"iteration":756,"passed_time":0.2095610805,"remaining_time":0.06726993732},
{"learn":[3.415160245],"iteration":757,"passed_time":0.2099389605,"remaining_time":0.06702536733},
{"learn":[3.412854597],"iteration":758,"passed_time":0.2101887555,"remaining_time":0.06673977611},
{"learn":[3.410926347],"iteration":759,"passed_time":0.2104103418,"remaining_time":0.06644537108},
{"learn":[3.408963843],"iteration":760,"passed_time":0.2106181779,"remaining_time":0.06614683904},
{"learn":[3.407629634],"iteration":761,"passed_time":0.2108331391,"remaining_time":0.06585077047},
{"learn":[3.404384724],"iteration":762,"passed_time":0.2110936842,"remaining_time":0.06556907359},
{"learn":[3.403041656],"iteration":763,"passed_time":0.2113348541,"remaining_time":0.06528144707},
{"learn":[3.401101731],"iteration":764,"passed_time":0.2115324817,"remaining_time":0.06498056627},
{"learn":[3.400890668],"iteration":765,"passed_time":0.2117393178,"remaining_time":0.06468276809},
{"learn":[3.399289941],"iteration":766,"passed_time":0.2119384038,"remaining_time":0.06438285277},
{"learn":[3.399202366],"iteration":767,"passed_time":0.2121314063,"remaining_time":0.06408136233},
{"learn":[3.397447845],"iteration":768,"passed_time":0.2123254506,"remaining_time":0.06378046695},
{"learn":[3.394655341],"iteration":769,"passed_time":0.2125627037,"remaining_time":0.06349275566},
{"learn":[3.393228229],"iteration":770,"passed_time":0.2127706232,"remaining_time":0.06319646265},
{"learn":[3.389691197],"iteration":771,"passed_time":0.2129589173,"remaining_time":0.06289460253},
{"learn":[3.389626772],"iteration":772,"passed_time":0.2131564616,"remaining_time":0.06259575264},
{"learn":[3.388480222],"iteration":773,"passed_time":0.2133508809,"remaining_time":0.06229625204},
{"learn":[3.388215066],"iteration":774,"passed_time":0.2135744255,"remaining_time":0.06200547838},
{"learn":[3.386324358],"iteration":775,"passed_time":0.2138485959,"remaining_time":0.06172949159},
{"learn":[3.383913061],"iteration":776,"passed_time":0.2141050993,"remaining_time":0.06144843904},
{"learn":[3.382839768],"iteration":777,"passed_time":0.2142943518,"remaining_time":0.06114825976},
{"learn":[3.381961844],"iteration":778,"passed_time":0.2145388967,"remaining_time":0.06086405157},
{"learn":[3.381521703],"iteration":779,"passed_time":0.2147447328,"remaining_time":0.06056902719},
{"learn":[3.380918963],"iteration":780,"passed_time":0.2149322769,"remaining_time":0.06026910198},
{"learn":[3.377139006],"iteration":781,"passed_time":0.215140738,"remaining_time":0.05997529526},
{"learn":[3.376004372],"iteration":782,"passed_time":0.2153381157,"remaining_time":0.05967863487},
{"learn":[3.373826468],"iteration":783,"passed_time":0.2155212848,"remaining_time":0.05937831315},
{"learn":[3.373546786],"iteration":784,"passed_time":0.2157089956,"remaining_time":0.05907953383},
{"learn":[3.372109181],"iteration":785,"passed_time":0.2158954148,"remaining_time":0.05878068544},
{"learn":[3.370764924],"iteration":786,"passed_time":0.2160825006,"remaining_time":0.05848230321},
{"learn":[3.367833107],"iteration":787,"passed_time":0.216268128,"remaining_time":0.0581838111},
{"learn":[3.36450404],"iteration":788,"passed_time":0.2164770892,"remaining_time":0.05789184514},
{"learn":[3.361794558],"iteration":789,"passed_time":0.2166974671,"remaining_time":0.05760312416},
{"learn":[3.356880529],"iteration":790,"passed_time":0.2168992614,"remaining_time":0.05730966579},
{"learn":[3.353843509],"iteration":791,"passed_time":0.2170858889,"remaining_time":0.05701245568},
{"learn":[3.353640253],"iteration":792,"passed_time":0.217269683,"remaining_time":0.05671478486},
{"learn":[3.353055088],"iteration":793,"passed_time":0.2174537688,"remaining_time":0.05641747655},
{"learn":[3.351415617],"iteration":794,"passed_time":0.2176343962,"remaining_time":0.05611956129},
{"learn":[3.349169061],"iteration":795,"passed_time":0.2178180653,"remaining_time":0.05582272026},
{"learn":[3.346211014],"iteration":796,"passed_time":0.2180134429,"remaining_time":0.05552914544},
{"learn":[3.344560452],"iteration":797,"passed_time":0.2181992787,"remaining_time":0.05523340139},
{"learn":[3.344445461],"iteration":798,"passed_time":0.2183856979,"remaining_time":0.0549380792},
{"learn":[3.342608898],"iteration":799,"passed_time":0.2185792421,"remaining_time":0.05464481053},
{"learn":[3.339572899],"iteration":800,"passed_time":0.2187585362,"remaining_time":0.05434825056},
{"learn":[3.339309302],"iteration":801,"passed_time":0.2189384136,"remaining_time":0.05405212704},
{"learn":[3.33698088],"iteration":802,"passed_time":0.2191150409,"remaining_time":0.05375549572},
{"learn":[3.334746342],"iteration":803,"passed_time":0.2192978767,"remaining_time":0.05346067641},
{"learn":[3.332048511],"iteration":804,"passed_time":0.2195387966,"remaining_time":0.05318020538},
{"learn":[3.331932544],"iteration":805,"passed_time":0.2197325075,"remaining_time":0.05288846954},
{"learn":[3.330541133],"iteration":806,"passed_time":0.2199393852,"remaining_time":0.05260012559},
{"learn":[3.329124989],"iteration":807,"passed_time":0.2201366379,"remaining_time":0.05230969613},
{"learn":[3.32583918],"iteration":808,"passed_time":0.220324307,"remaining_time":0.05201723442},
{"learn":[3.325287299],"iteration":809,"passed_time":0.2205158096,"remaining_time":0.05172593064},
{"learn":[3.322745162],"iteration":810,"passed_time":0.2207110622,"remaining_time":0.05143574692},
{"learn":[3.319733662],"iteration":811,"passed_time":0.2209294401,"remaining_time":0.05115115115},
{"learn":[3.318080007],"iteration":812,"passed_time":0.2211300261,"remaining_time":0.05086262593},
{"learn":[3.317179538],"iteration":813,"passed_time":0.2213199869,"remaining_time":0.05057188891},
{"learn":[3.315685949],"iteration":814,"passed_time":0.2215108645,"remaining_time":0.05028160728},
{"learn":[3.314944576],"iteration":815,"passed_time":0.2217084921,"remaining_time":0.04999309136},
{"learn":[3.312369052],"iteration":816,"passed_time":0.2219235366,"remaining_time":0.04970869915},
{"learn":[3.312321621],"iteration":817,"passed_time":0.2220590801,"remaining_time":0.049406788},
{"learn":[3.309465776],"iteration":818,"passed_time":0.2222539994,"remaining_time":0.04911840523},
{"learn":[3.308307377],"iteration":819,"passed_time":0.222448002,"remaining_time":0.04883004921},
{"learn":[3.308076804],"iteration":820,"passed_time":0.2226292127,"remaining_time":0.04853913407},
{"learn":[3.305643326],"iteration":821,"passed_time":0.2228157569,"remaining_time":0.04824964078},
{"learn":[3.304154814],"iteration":822,"passed_time":0.2229938009,"remaining_time":0.04795856957},
{"learn":[3.303076321],"iteration":823,"passed_time":0.2231939702,"remaining_time":0.04767249849},
{"learn":[3.301746372],"iteration":824,"passed_time":0.2233902228,"remaining_time":0.04738580484},
{"learn":[3.301345455],"iteration":825,"passed_time":0.2236131425,"remaining_time":0.04710494769},
{"learn":[3.299181039],"iteration":826,"passed_time":0.2238326871,"remaining_time":0.04682352462},
{"learn":[3.297989357],"iteration":827,"passed_time":0.2240031477,"remaining_time":0.04653205483},
{"learn":[3.294775182],"iteration":828,"passed_time":0.2241874418,"remaining_time":0.04624373045},
{"learn":[3.293840636],"iteration":829,"passed_time":0.224378861,"remaining_time":0.04595711611},
{"learn":[3.289279397],"iteration":830,"passed_time":0.2245979889,"remaining_time":0.04567636597},
{"learn":[3.286204979],"iteration":831,"passed_time":0.2247926582,"remaining_time":0.04539082521},
{"learn":[3.284833593],"iteration":832,"passed_time":0.2249876608,"remaining_time":0.04510556944},
{"learn":[3.283519914],"iteration":833,"passed_time":0.2251694965,"remaining_time":0.04481790938},
{"learn":[3.282853026],"iteration":834,"passed_time":0.2253357487,"remaining_time":0.0445274234},
{"learn":[3.281944673],"iteration":835,"passed_time":0.2255132927,"remaining_time":0.04423944977},
{"learn":[3.279764865],"iteration":836,"passed_time":0.2256870867,"remaining_time":0.04395100972},
{"learn":[3.277468839],"iteration":837,"passed_time":0.2258831727,"remaining_time":0.04366715271},
{"learn":[3.277124974],"iteration":838,"passed_time":0.2260720502,"remaining_time":0.04338212167},
{"learn":[3.275636037],"iteration":839,"passed_time":0.2270290213,"remaining_time":0.0432436231},
{"learn":[3.274413635],"iteration":840,"passed_time":0.2272530242,"remaining_time":0.04296460268},
{"learn":[3.272636087],"iteration":841,"passed_time":0.2275048609,"remaining_time":0.0426909359},
{"learn":[3.269644466],"iteration":842,"passed_time":0.2277046136,"remaining_time":0.0424076208},
{"learn":[3.26852083],"iteration":843,"passed_time":0.2279005745,"remaining_time":0.04212380287},
{"learn":[3.267820927],"iteration":844,"passed_time":0.2280986605,"remaining_time":0.04184058269},
{"learn":[3.267331099],"iteration":845,"passed_time":0.2282857046,"remaining_time":0.0415555538},
{"learn":[3.267231014],"iteration":846,"passed_time":0.2285323329,"remaining_time":0.04128151941},
{"learn":[3.267158695],"iteration":847,"passed_time":0.2287785029,"remaining_time":0.0410074675},
{"learn":[3.264718705],"iteration":848,"passed_time":0.2289674637,"remaining_time":0.04072330627},
{"learn":[3.261678512],"iteration":849,"passed_time":0.2291595496,"remaining_time":0.04043992052},
{"learn":[3.261368381],"iteration":850,"passed_time":0.2293623856,"remaining_time":0.04015863156},
{"learn":[3.260128799],"iteration":851,"passed_time":0.22956218,"remaining_time":0.0398769984},
{"learn":[3.258972952],"iteration":852,"passed_time":0.2297581826,"remaining_time":0.03959490368},
{"learn":[3.258724846],"iteration":853,"passed_time":0.2299989774,"remaining_time":0.03932066827},
{"learn":[3.25686724],"iteration":854,"passed_time":0.230213272,"remaining_time":0.03904201688},
{"learn":[3.255750259],"iteration":855,"passed_time":0.2304113579,"remaining_time":0.03876078918},
{"learn":[3.254915866],"iteration":856,"passed_time":0.230593527,"remaining_time":0.03847709961},
{"learn":[3.254348625],"iteration":857,"passed_time":0.2307994048,"remaining_time":0.03819757049},
{"learn":[3.253408514],"iteration":858,"passed_time":0.2309981574,"remaining_time":0.0379170433},
{"learn":[3.253291714],"iteration":859,"passed_time":0.2311774515,"remaining_time":0.03763353861},
{"learn":[3.250186342],"iteration":860,"passed_time":0.2313583705,"remaining_time":0.03735053833},
{"learn":[3.249141318],"iteration":861,"passed_time":0.2315392063,"remaining_time":0.03706776156},
{"learn":[3.246300388],"iteration":862,"passed_time":0.231746209,"remaining_time":0.03678937501},
{"learn":[3.245205135],"iteration":863,"passed_time":0.2319353365,"remaining_time":0.03650834001},
{"learn":[3.244403535],"iteration":864,"passed_time":0.2321289641,"remaining_time":0.03622821983},
{"learn":[3.244211781],"iteration":865,"passed_time":0.2323421753,"remaining_time":0.03595132966},
{"learn":[3.242286347],"iteration":866,"passed_time":0.2325255527,"remaining_time":0.03567000982},
{"learn":[3.239606746],"iteration":867,"passed_time":0.2327250554,"remaining_time":0.03539136787},
{"learn":[3.236773361],"iteration":868,"passed_time":0.2329120162,"remaining_time":0.0351110174},
{"learn":[3.234552446],"iteration":869,"passed_time":0.2331305191,"remaining_time":0.03483559481},
{"learn":[3.233724647],"iteration":870,"passed_time":0.2333339385,"remaining_time":0.03455806896},
{"learn":[3.230851485],"iteration":871,"passed_time":0.2335315245,"remaining_time":0.0342798568},
{"learn":[3.227728941],"iteration":872,"passed_time":0.2337304854,"remaining_time":0.03400202938},
{"learn":[3.225787575],"iteration":873,"passed_time":0.2339417799,"remaining_time":0.03372616049},
{"learn":[3.222797487],"iteration":874,"passed_time":0.2341677829,"remaining_time":0.03345254042},
{"learn":[3.22137014],"iteration":875,"passed_time":0.2343389102,"remaining_time":0.03317126126},
{"learn":[3.219701963],"iteration":876,"passed_time":0.2345305794,"remaining_time":0.03289311433},
{"learn":[3.21783327],"iteration":877,"passed_time":0.2347098735,"remaining_time":0.03261344483},
{"learn":[3.217713355],"iteration":878,"passed_time":0.2348982093,"remaining_time":0.03233524838},
{"learn":[3.217666091],"iteration":879,"passed_time":0.235074045,"remaining_time":0.03205555159},
{"learn":[3.214962005],"iteration":880,"passed_time":0.235327715,"remaining_time":0.03178660396},
{"learn":[3.214081828],"iteration":881,"passed_time":0.2355147592,"remaining_time":0.03150877731},
{"learn":[3.213358337],"iteration":882,"passed_time":0.2357013033,"remaining_time":0.03123109002},
{"learn":[3.210850401],"iteration":883,"passed_time":0.2358934726,"remaining_time":0.03095434708},
{"learn":[3.207810328],"iteration":884,"passed_time":0.2360668915,"remaining_time":0.03067535879},
{"learn":[3.204935073],"iteration":885,"passed_time":0.2362661025,"remaining_time":0.03039992741},
{"learn":[3.20280198],"iteration":886,"passed_time":0.2364526883,"remaining_time":0.03012305951},
{"learn":[3.200663495],"iteration":887,"passed_time":0.2366393575,"remaining_time":0.02984640545},
{"learn":[3.197301669],"iteration":888,"passed_time":0.23682811,"remaining_time":0.02957021396},
{"learn":[3.195666943],"iteration":889,"passed_time":0.2370253626,"remaining_time":0.02929526954},
{"learn":[3.193886506],"iteration":890,"passed_time":0.2372088651,"remaining_time":0.02901881739},
{"learn":[3.190601248],"iteration":891,"passed_time":0.2373976592,"remaining_time":0.02874321435},
{"learn":[3.188983797],"iteration":892,"passed_time":0.2375882034,"remaining_time":0.02846801542},
{"learn":[3.187365749],"iteration":893,"passed_time":0.2377888311,"remaining_time":0.02819420145},
{"learn":[3.186160771],"iteration":894,"passed_time":0.2379861671,"remaining_time":0.02792016485},
{"learn":[3.185358981],"iteration":895,"passed_time":0.2381902948,"remaining_time":0.02764708779},
{"learn":[3.183832164],"iteration":896,"passed_time":0.2383668388,"remaining_time":0.0273709971},
{"learn":[3.183106966],"iteration":897,"passed_time":0.238558383,"remaining_time":0.02709683192},
{"learn":[3.182838152],"iteration":898,"passed_time":0.2387382604,"remaining_time":0.02682153982},
{"learn":[3.180835453],"iteration":899,"passed_time":0.2389483049,"remaining_time":0.02654981165},
{"learn":[3.179957348],"iteration":900,"passed_time":0.2391478075,"remaining_time":0.02627706209},
{"learn":[3.179752966],"iteration":901,"passed_time":0.2393424351,"remaining_time":0.02600394528},
{"learn":[3.178851983],"iteration":902,"passed_time":0.2395483545,"remaining_time":0.02573221527},
{"learn":[3.176748586],"iteration":903,"passed_time":0.2397371487,"remaining_time":0.02545881225},
{"learn":[3.172960988],"iteration":904,"passed_time":0.2399408597,"remaining_time":0.02518716207},
{"learn":[3.172794225],"iteration":905,"passed_time":0.2401307789,"remaining_time":0.02491423093},
{"learn":[3.169996507],"iteration":906,"passed_time":0.2403299483,"remaining_time":0.0246424313},
{"learn":[3.16813015],"iteration":907,"passed_time":0.2405264925,"remaining_time":0.02437052568},
{"learn":[3.166920871],"iteration":908,"passed_time":0.2407368703,"remaining_time":0.02410017074},
{"learn":[3.16531606],"iteration":909,"passed_time":0.2409556649,"remaining_time":0.02383078005},
{"learn":[3.162035247],"iteration":910,"passed_time":0.2411551259,"remaining_time":0.02355961164},
{"learn":[3.16189467],"iteration":911,"passed_time":0.2413551702,"remaining_time":0.02328865678},
{"learn":[3.161008416],"iteration":912,"passed_time":0.2415968401,"remaining_time":0.02302182376},
{"learn":[3.160560787],"iteration":913,"passed_time":0.2417852593,"remaining_time":0.02275003534},
{"learn":[3.160416261],"iteration":914,"passed_time":0.2419856786,"remaining_time":0.02247954392},
{"learn":[3.15844291],"iteration":915,"passed_time":0.2421981815,"remaining_time":0.02221031358},
{"learn":[3.155040501],"iteration":916,"passed_time":0.2423954341,"remaining_time":0.02193982664},
{"learn":[3.154937548],"iteration":917,"passed_time":0.2426349789,"remaining_time":0.02167327699},
{"learn":[3.153721161],"iteration":918,"passed_time":0.2428259398,"remaining_time":0.02140250394},
{"learn":[3.153170511],"iteration":919,"passed_time":0.243016734,"remaining_time":0.02113188991},
{"learn":[3.153113601],"iteration":920,"passed_time":0.2432046948,"remaining_time":0.02086120618},
{"learn":[3.150607379],"iteration":921,"passed_time":0.2434687817,"remaining_time":0.02059714205},
{"learn":[3.148408359],"iteration":922,"passed_time":0.2437489938,"remaining_time":0.0203344231},
{"learn":[3.147495728],"iteration":923,"passed_time":0.2439576632,"remaining_time":0.02006578182},
{"learn":[3.146946235],"iteration":924,"passed_time":0.2441379989,"remaining_time":0.01979497289},
{"learn":[3.14472738],"iteration":925,"passed_time":0.2443337515,"remaining_time":0.01952559138},
{"learn":[3.144469477],"iteration":926,"passed_time":0.244521004,"remaining_time":0.01925569935},
{"learn":[3.142975516],"iteration":927,"passed_time":0.2447092982,"remaining_time":0.01898606624},
{"learn":[3.14079113],"iteration":928,"passed_time":0.2448953423,"remaining_time":0.01871643628},
{"learn":[3.138173032],"iteration":929,"passed_time":0.2450962617,"remaining_time":0.01844810572},
{"learn":[3.136352813],"iteration":930,"passed_time":0.2452866809,"remaining_time":0.01817914176},
{"learn":[3.133735004],"iteration":931,"passed_time":0.2454713917,"remaining_time":0.01790992987},
{"learn":[3.1319496],"iteration":932,"passed_time":0.2456672693,"remaining_time":0.01764170101},
{"learn":[3.129865343],"iteration":933,"passed_time":0.2458669803,"remaining_time":0.01737389796},
{"learn":[3.129830206],"iteration":934,"passed_time":0.2459987737,"remaining_time":0.01710151903},
{"learn":[3.126676562],"iteration":935,"passed_time":0.2462011097,"remaining_time":0.01683426391},
{"learn":[3.12645665],"iteration":936,"passed_time":0.2463830705,"remaining_time":0.01656577742},
{"learn":[3.126378007],"iteration":937,"passed_time":0.2465808648,"remaining_time":0.01629852198},
{"learn":[3.124621914],"iteration":938,"passed_time":0.2467794924,"remaining_time":0.01603146862},
{"learn":[3.123379018],"iteration":939,"passed_time":0.2469701616,"remaining_time":0.01576405287},
{"learn":[3.123332451],"iteration":940,"passed_time":0.2471749143,"remaining_time":0.01549768326},
{"learn":[3.122432444],"iteration":941,"passed_time":0.2473864588,"remaining_time":0.01523186265},
{"learn":[3.121889006],"iteration":942,"passed_time":0.2475795031,"remaining_time":0.01496503889},
{"learn":[3.121070914],"iteration":943,"passed_time":0.2477672556,"remaining_time":0.01469805753},
{"learn":[3.118444705],"iteration":944,"passed_time":0.2479773417,"remaining_time":0.0144325437},
{"learn":[3.116820458],"iteration":945,"passed_time":0.2481803444,"remaining_time":0.0141667427},
{"learn":[3.114971041],"iteration":946,"passed_time":0.248377972,"remaining_time":0.01390077351},
{"learn":[3.114685138],"iteration":947,"passed_time":0.248580058,"remaining_time":0.01363519306},
{"learn":[3.113399363],"iteration":948,"passed_time":0.2487770607,"remaining_time":0.01336947323},
{"learn":[3.110575399],"iteration":949,"passed_time":0.2489868968,"remaining_time":0.01310457352},
{"learn":[3.110466553],"iteration":950,"passed_time":0.2491668159,"remaining_time":0.01283824814},
{"learn":[3.108691641],"iteration":951,"passed_time":0.2493889855,"remaining_time":0.01257423456},
{"learn":[3.107898017],"iteration":952,"passed_time":0.2496157802,"remaining_time":0.0123105369},
{"learn":[3.105551729],"iteration":953,"passed_time":0.2498546583,"remaining_time":0.01204749925},
{"learn":[3.104824945],"iteration":954,"passed_time":0.2500367024,"remaining_time":0.01178183415},
{"learn":[3.103186704],"iteration":955,"passed_time":0.2502326634,"remaining_time":0.01151698451},
{"learn":[3.102330655],"iteration":956,"passed_time":0.2504405828,"remaining_time":0.01125281616},
{"learn":[3.102291298],"iteration":957,"passed_time":0.2506276686,"remaining_time":0.01098785186},
{"learn":[3.100363529],"iteration":958,"passed_time":0.2508169628,"remaining_time":0.0107231444},
{"learn":[3.097871596],"iteration":959,"passed_time":0.2510098404,"remaining_time":0.01045874335},
{"learn":[3.097372213],"iteration":960,"passed_time":0.2512219265,"remaining_time":0.01019527069},
{"learn":[3.095981813],"iteration":961,"passed_time":0.2514117624,"remaining_time":0.009931025958},
{"learn":[3.095347452],"iteration":962,"passed_time":0.2515882231,"remaining_time":0.009666421863},
{"learn":[3.094728409],"iteration":963,"passed_time":0.2517698505,"remaining_time":0.009402193587},
{"learn":[3.094118537],"iteration":964,"passed_time":0.2519662281,"remaining_time":0.009138671486},
{"learn":[3.093793695],"iteration":965,"passed_time":0.2521386887,"remaining_time":0.008874446602},
{"learn":[3.092581602],"iteration":966,"passed_time":0.2523839837,"remaining_time":0.008612897064},
{"learn":[3.091694202],"iteration":967,"passed_time":0.252581778,"remaining_time":0.008349810842},
{"learn":[3.090298312],"iteration":968,"passed_time":0.252785989,"remaining_time":0.008087064664},
{"learn":[3.090020107],"iteration":969,"passed_time":0.2530571593,"remaining_time":0.007826510081},
{"learn":[3.088949869],"iteration":970,"passed_time":0.2532589536,"remaining_time":0.007563861643},
{"learn":[3.086700204],"iteration":971,"passed_time":0.253438956,"remaining_time":0.007300710668},
{"learn":[3.086584317],"iteration":972,"passed_time":0.253635542,"remaining_time":0.007038190785},
{"learn":[3.084850742],"iteration":973,"passed_time":0.2538417114,"remaining_time":0.006776062111},
{"learn":[3.084239948],"iteration":974,"passed_time":0.2540392974,"remaining_time":0.006513828138},
{"learn":[3.082561673],"iteration":975,"passed_time":0.2542266332,"remaining_time":0.006251474587},
{"learn":[3.07991814],"iteration":976,"passed_time":0.2544218025,"remaining_time":0.005989459014},
{"learn":[3.079350277],"iteration":977,"passed_time":0.2546262218,"remaining_time":0.005727788221},
{"learn":[3.077637462],"iteration":978,"passed_time":0.2548286412,"remaining_time":0.005466191487},
{"learn":[3.076733301],"iteration":979,"passed_time":0.255015602,"remaining_time":0.005204400041},
{"learn":[3.07594065],"iteration":980,"passed_time":0.2552345633,"remaining_time":0.00494338094},
{"learn":[3.072594655],"iteration":981,"passed_time":0.2554217324,"remaining_time":0.004681864749},
{"learn":[3.071977674],"iteration":982,"passed_time":0.2556229434,"remaining_time":0.004420742664},
{"learn":[3.069532634],"iteration":983,"passed_time":0.2558274462,"remaining_time":0.004159795873},
{"learn":[3.068870784],"iteration":984,"passed_time":0.2560170737,"remaining_time":0.003898737163},
{"learn":[3.068801463],"iteration":985,"passed_time":0.2562022845,"remaining_time":0.003637760632},
{"learn":[3.067433249],"iteration":986,"passed_time":0.2563983704,"remaining_time":0.003377080867},
{"learn":[3.065611456],"iteration":987,"passed_time":0.2566118316,"remaining_time":0.003116742894},
{"learn":[3.063039162],"iteration":988,"passed_time":0.2568074592,"remaining_time":0.002856301366},
{"learn":[3.06177873],"iteration":989,"passed_time":0.2570025451,"remaining_time":0.002595985304},
{"learn":[3.061689148],"iteration":990,"passed_time":0.2571840059,"remaining_time":0.002335677147},
{"learn":[3.058984039],"iteration":991,"passed_time":0.2573748834,"remaining_time":0.002075603899},
{"learn":[3.057492984],"iteration":992,"passed_time":0.2575580109,"remaining_time":0.001815615384},
{"learn":[3.057290731],"iteration":993,"passed_time":0.2577343465,"remaining_time":0.001555740522},
{"learn":[3.056068348],"iteration":994,"passed_time":0.2579200573,"remaining_time":0.00129608069},
{"learn":[3.054987307],"iteration":995,"passed_time":0.2581096015,"remaining_time":0.001036584745},
{"learn":[3.054200234],"iteration":996,"passed_time":0.2583793551,"remaining_time":0.0007774704768},
{"learn":[3.052732869],"iteration":997,"passed_time":0.2586508171,"remaining_time":0.0005183383108},
{"learn":[3.051787862],"iteration":998,"passed_time":0.2589304875,"remaining_time":0.0002591896771},
{"learn":[3.051366222],"iteration":999,"passed_time":0.2591410736,"remaining_time":0}
]}